{"music":[{"artist":{"name":"Lionel Richie"},"song":{"id":"SOBONFF12A6D4F84D8","title":"Tonight Will Be Alright"}},{"artist":{"name":"Roberto Torres"},"song":{"id":"SOHGKJW12AC468A8BD","title":"Sabor Guajiro"}},{"artist":{"name":"R.L. Burnside"},"song":{"id":"SOTWVQT12A58A79650","title":"Glory Be"}},{"artist":{"name":"John Hammond"},"song":{"id":"SOTSETT12AB01863B8","title":"I Can\u0027t Be Satisfied"}},{"artist":{"name":"The New York Dolls"},"song":{"id":"SOGKIWV12A6D4F86C4","title":"Human Being"}},{"artist":{"name":"The Berzerker"},"song":{"id":"SOYWZTU12AB0180E26","title":"Deform (live)"}},{"artist":{"name":"Heavy D / McGruff"},"song":{"id":"SOFZCTA12AB0188D8F","title":"Wanna Be A Player"}},{"artist":{"name":"Glen Campbell"},"song":{"id":"SOQGFVO12A8C13C8C3","title":"I\u0027m Gone This Time"}},{"artist":{"name":"Savage Garden"},"song":{"id":"SOMQAGT12A8C132DB4","title":"You Can Still Be Free"}},{"artist":{"name":"The Brooklyn Tabernacle Choir"},"song":{"id":"SOXVBVL12AF72A600C","title":"Lead Me Lord"}},{"artist":{"name":"Nazz"},"song":{"id":"SOYPBCY12AB0181EF3","title":"How Can You Call That Beautiful (Stewkey Vocal)"}},{"artist":{"name":"Boyz II Men"},"song":{"id":"SOFRAZJ12A8C143CDB","title":"On Bended Knee"}},{"artist":{"name":"Saafir"},"song":{"id":"SOFDTRZ12AB018DD11","title":"Crawl Before You Ball (Album Version)"}},{"artist":{"name":"Robben Ford"},"song":{"id":"SOOSYMY12AB01888CD","title":"I Got Over It (Album Version)"}},{"artist":{"name":"Brazilian Tropical Orchestra"},"song":{"id":"SOPBKEB12A6D4FD777","title":"One Less Bell To Answer"}},{"artist":{"name":"BT"},"song":{"id":"SONXLQQ12AB0184B54","title":"Robbers Kill Cop"}},{"artist":{"name":"Norrie Paramor"},"song":{"id":"SOFGQAP12AB0185946","title":"Dearly Beloved"}},{"artist":{"name":"Pery Ribeiro"},"song":{"id":"SOUDHTP12AB0183403","title":"Our Love Is Here To Stay"}},{"artist":{"name":"Ana Bekuta"},"song":{"id":"SOQPJUL12AB0189379","title":"Kako mi je pitas sad"}},{"artist":{"name":"Bebo \u0026 Cigala"},"song":{"id":"SOKEXTF12A8C13AE7E","title":"Inolvidable"}},{"artist":{"name":"S.U.P"},"song":{"id":"SOIFOLA12AB017CDA1","title":"The Cube (Live)"}},{"artist":{"name":"Aberdeen"},"song":{"id":"SOOZKNQ12A6D4F6FD4","title":"Beyond the Light"}},{"artist":{"name":"Rise Against"},"song":{"id":"SOSKUNI12AB0187F12","title":"Amber Changing"}},{"artist":{"name":"Korn"},"song":{"id":"SOVHRBI12A81C22E02","title":"Ever Be"}},{"artist":{"name":"Jimmy Wakely"},"song":{"id":"SOHCYVK12AB017BBF2","title":"Beautiful Brown eyes"}},{"artist":{"name":"Bert Kaempfert And His Orchestra"},"song":{"id":"SOHGAJH12A6D4F8F58","title":"Just As Much As Ever"}},{"artist":{"name":"Carl Belew"},"song":{"id":"SOGJSEF12AB01847D4","title":"Love\u0027s Been Good To Me"}},{"artist":{"name":"Billy Higgins_ Bob Berg_ Cedar Walton_ Tony Dumas"},"song":{"id":"SOGVRHK12A8AE47FFB","title":"Estate"}},{"artist":{"name":"Tiny Tim"},"song":{"id":"SOAOIBZ12AB01815BE","title":"I Hold Your Hand In Mine [Live At Royal Albert Hall]"}},{"artist":{"name":"David Martin"},"song":{"id":"SOTTDKS12AB018D69B","title":"It Wont Be Christmas"}},{"artist":{"name":"Sophie B. Hawkins"},"song":{"id":"SONWXQJ12A8C134D94","title":"The Ballad Of Sleeping Beauty"}},{"artist":{"name":"Leon Russell \u0026 New Grass Revival"},"song":{"id":"SOHNDEQ12A6D4F9FBE","title":"Truck Driving Man/Down In The Caribbean"}},{"artist":{"name":"Neil Sedaka"},"song":{"id":"SOIUJEF12A8C13C878","title":"Because Of You"}},{"artist":{"name":"Jauida"},"song":{"id":"SORZLRP12AB017D68D","title":"I don\u0027t Want to Be Alone Tonight"}},{"artist":{"name":"Regina Belle"},"song":{"id":"SOWHNGE12A8C133D07","title":"Quiet Time"}},{"artist":{"name":"Jeanie Lambe \u0026 The Danny Moss Quartet"},"song":{"id":"SOCYAKZ12AB018708F","title":"Saturday Night Is The Loneliest Night In The Week"}},{"artist":{"name":"VHS Or Beta"},"song":{"id":"SOFRROW12A6701CBEA","title":"The Melting Moon (Edit)"}},{"artist":{"name":"True Believers"},"song":{"id":"SOCPSFM12A8C136A50","title":"Turn Around"}},{"artist":{"name":"Beatnuts"},"song":{"id":"SOTNQRU12A8C131FEF","title":"Monster For Music"}},{"artist":{"name":"Oztara"},"song":{"id":"SOTAGIH12AB018152A","title":"La Route Est Belle"}},{"artist":{"name":"The Police"},"song":{"id":"SOSHODS12A6D4F79BC","title":"When The World Is Running Down_ You Make The Best Of What\u0027s Still Around"}},{"artist":{"name":"Shriekback"},"song":{"id":"SOBXYZM12A8C140450","title":"Reason With The Beast"}},{"artist":{"name":"Owl City"},"song":{"id":"SOEVPYU12CF5827356","title":"Panda Bear"}},{"artist":{"name":"Canis Dirus"},"song":{"id":"SOBEVMI12AB018E480","title":"A Somber Wind from a Distant Shore (Album)"}},{"artist":{"name":"Gaetano Donizetti"},"song":{"id":"SOMKWCF12A8C142BCD","title":"Donizetti: Roberto Devereux: L\u0027ore trascorrono..."}},{"artist":{"name":"Maysa"},"song":{"id":"SOKZYGT12A8C139568","title":"This Time I\u0027ll Be Sweeter"}},{"artist":{"name":"Neil Innes"},"song":{"id":"SOMRFYS12A8C13CCA4","title":"Lie Down And Be Counted (2007 Digital Remaster)"}},{"artist":{"name":"Regina Belle"},"song":{"id":"SOVGKBD12AAF3B4FFB","title":"If I Ruled The World"}},{"artist":{"name":"Green Day"},"song":{"id":"SOWQROJ12A8AE47400","title":"Wake Me Up When September Ends (Live at Foxboro_ MA 9/3/05)"}},{"artist":{"name":"Becky Baeling"},"song":{"id":"SOQVGKZ12A6D4F8244","title":"If You Love Me"}},{"artist":{"name":"Laurie Berkner"},"song":{"id":"SOFJWKK12AB01826CD","title":"The Cookie Bakers of the Night"}},{"artist":{"name":"Beenie Man Featuring Wyclef And Redman"},"song":{"id":"SOJRNQF12A8C134D57","title":"Love Me Now (Rockwilder Remix) (Feat. Wyclef And Redman)"}},{"artist":{"name":"Robben Ford"},"song":{"id":"SOVKUOE12A58A8066E","title":"Something For The Pain"}},{"artist":{"name":"Jeff Beck"},"song":{"id":"SOFDOAD12A58A7BAD3","title":"A Day In The Life (Album Version)"}},{"artist":{"name":"Fudge Tunnel"},"song":{"id":"SOZTDIN12AB018AAD1","title":"Bed Crumbs"}},{"artist":{"name":"GG Allin"},"song":{"id":"SODUNOD12A58A79381","title":"I Live to Be Hated"}},{"artist":{"name":"Daniel Johnston"},"song":{"id":"SOHWWOM12AB0186627","title":"Story Of An Artist (Don\u0027t Be Scared)"}},{"artist":{"name":"JoAPSo Gilberto"},"song":{"id":"SODPNJR12A6D4FA52D","title":"Segredo"}},{"artist":{"name":"Muse"},"song":{"id":"SOMMSMW12A8C13FCCC","title":"Bedroom Acoustics"}},{"artist":{"name":"Enthroned"},"song":{"id":"SOHCCIA12AC907577F","title":"Ad Te Clamamus Exsvles Mortva Liberi"}},{"artist":{"name":"Vanessa Bell Armstrong"},"song":{"id":"SOCUDXX12A58A76EF9","title":"Til The Victory\u0027s Won"}},{"artist":{"name":"Bersuit Vergarabat"},"song":{"id":"SONTEWC12AB0186E51","title":"Sencillamente"}},{"artist":{"name":"Steve Riley \u0026 The Mamou Playboys"},"song":{"id":"SOQBETA12CF5702399","title":"Between Eunice \u0026 Opelousas"}},{"artist":{"name":"David Martin"},"song":{"id":"SOHWKQE12A8C142406","title":"It Must Be"}},{"artist":{"name":"Autumnblaze"},"song":{"id":"SOZNBMX12AB0182AD1","title":"Her Golden Robe In Silence Veiled"}},{"artist":{"name":"Bamberg Symphony Orchestra and Hans Swarowsky"},"song":{"id":"SOOOJUT12AB01883B9","title":"Hungarian Dances_ WoO 1: No. 12 in D Minor: Presto"}},{"artist":{"name":"Ty Herndon;Stephanie Bentley"},"song":{"id":"SOVWNAS12A8C130573","title":"Heart Half Empty"}},{"artist":{"name":"Sonny Terry \u0026 Brownie McGhee"},"song":{"id":"SOPOZOQ12A58A76660","title":"Be Good To Me"}},{"artist":{"name":"Enslavement Of Beauty"},"song":{"id":"SOIKOBP12AB01897DA","title":"Ye That Tempteth_ Ye That Bequeth"}},{"artist":{"name":"Behemoth"},"song":{"id":"SOBXGKH12AB017DDB6","title":"Before The Aons Came"}},{"artist":{"name":"RamA3n Vargas_ SA$?ngerknaben Luzerner Kantorei_ Henk Geuke_ Concilium Musicum Wien \u0026 Paul Angerer"},"song":{"id":"SOVYTTY12A8C131260","title":"Adeste fideles"}},{"artist":{"name":"Anubis Spire"},"song":{"id":"SOUHBIP12AF72A14DA","title":"It Has Been A Long Time_ Hasn\u0027t It"}},{"artist":{"name":"Beaver Harris"},"song":{"id":"SOUWBCT12AB01846F6","title":"Glo-Billy-Vee-Vee"}},{"artist":{"name":"Benabar"},"song":{"id":"SOADDVU12A8AE47512","title":"Le Zoo De Vincennes"}},{"artist":{"name":"True Believers"},"song":{"id":"SOCVTPO12A8C13414F","title":"I Worship You"}},{"artist":{"name":"Laid Back"},"song":{"id":"SOXUAQZ12AB0184442","title":"Maybe I\u0027m Crazy (Single original version_ 2008 Digital Remaster)"}},{"artist":{"name":"Agency 1.9.9.4"},"song":{"id":"SONHMQW12A8C13163C","title":"The Prayer - Feat. T.O. \u0026 Timberly K. Simmons"}},{"artist":{"name":"Ben Watt feat. Estelle"},"song":{"id":"SOZFLXY12A8C13A8E2","title":"Pop A Cap In Yo\u0027 Ass"}},{"artist":{"name":"Herbert  von Karajan"},"song":{"id":"SOKHIUI12A8C135F51","title":"Oedipus Rex_ Atto Secondo: Divum Jocastae Caput Mortuum (Messaggero_ Coro) (Stravinsky)"}},{"artist":{"name":"Bersuit Vergarabat"},"song":{"id":"SOMXGMJ12AB0183EC5","title":"Bolero Militar"}},{"artist":{"name":"Bebe Winans"},"song":{"id":"SOZOOYV12A6D4F445F","title":"Love Thing"}},{"artist":{"name":"Penguin CafA(c) Orchestra"},"song":{"id":"SOPEKCH12A6D4F66B3","title":"Bean Fields (Live) (2001 Digital Remaster)"}},{"artist":{"name":"Cornell Campbell"},"song":{"id":"SOXYGNC12A67021C29","title":"Give Your Love To Me"}},{"artist":{"name":"Alberto Cortez"},"song":{"id":"SOJKDEC12A8C131E8B","title":"Distancia"}},{"artist":{"name":"Pyrolator"},"song":{"id":"SOVLLLU12AB0185D84","title":"Gold Und Silber"}},{"artist":{"name":"Mudhoney"},"song":{"id":"SOEGWUQ12A5891CC6F","title":"Between Me \u0026 You Kid (Album Version)"}},{"artist":{"name":"Out Of The Grey"},"song":{"id":"SOQXUNA12A6D4F9AFB","title":"The One I\u0027ve Been Waiting For (Diamond Days Album Version)"}},{"artist":{"name":"X-ecutioners"},"song":{"id":"SOJQTNZ12AB018115B","title":"Play That Beat"}},{"artist":{"name":"Mario Rosenstock"},"song":{"id":"SOIVGSZ12AB017F898","title":"Bertie\u0027s Pets (Bonus Material)"}},{"artist":{"name":"Sister Hazel"},"song":{"id":"SOPXKFG12A58A78D97","title":"Space Between Us (Album Version)"}},{"artist":{"name":"Eddie Henderson"},"song":{"id":"SOUIAWC12AB018810E","title":"Beyond Forever (2004 Digital Remaster)"}},{"artist":{"name":"Cool For August"},"song":{"id":"SOUFVZJ12A6D4FA4FE","title":"Don\u0027t Wanna Be Here (Album Version)"}},{"artist":{"name":"Mat Kearney"},"song":{"id":"SOAPAIN12A8C142D08","title":"Never Be Ready"}},{"artist":{"name":"Julie Roberts"},"song":{"id":"SORTOKQ12AF72A545B","title":"Unlove Me"}},{"artist":{"name":"VHS Or Beta"},"song":{"id":"SOVIJEZ12A58A7F35C","title":"Solid Gold (Evolution Mix) (2005 Digital Remaster)"}},{"artist":{"name":"B.B. King"},"song":{"id":"SOFSDJY12AAF3B4381","title":"Please Remember Me"}},{"artist":{"name":"Marco Beltrami"},"song":{"id":"SOCWCPZ12AB018476F","title":"Past Meets Present"}},{"artist":{"name":"Tiny Tim"},"song":{"id":"SOOPNJS12AB0181570","title":"You Called It Madness [But I Call It Love] [Live At Royal Albert Hall]"}},{"artist":{"name":"The Brooklyn Tabernacle Choir"},"song":{"id":"SOYRUNW12AB01856B8","title":"All That You Need"}},{"artist":{"name":"The Shamen"},"song":{"id":"SOARKRH12AB0188703","title":"Heal (The Separation) [H.E.L.P Breakbeat]"}},{"artist":{"name":"Hubert Kah"},"song":{"id":"SOKECVO12A6D4F9F14","title":"Raketen"}},{"artist":{"name":"Dead Prez"},"song":{"id":"SOSYPCS12A8C136D12","title":"Be Healthy"}},{"artist":{"name":"Luis Alberto Spinetta"},"song":{"id":"SOWYXJC12A8C13B81E","title":"Verde Bosque"}},{"artist":{"name":"Robert Lockwood_ Jr."},"song":{"id":"SOHASWL12AB018352B","title":"She\u0027s Little And She\u0027s Low"}},{"artist":{"name":"Delbert McClinton"},"song":{"id":"SOIMSZI12AB0182252","title":"Lose Your Money"}},{"artist":{"name":"Gloria De Haven"},"song":{"id":"SOZECOE12AB017E615","title":"Diamonds Are A Girl\u0027s Best Friend"}},{"artist":{"name":"Rhian Benson"},"song":{"id":"SONLKRD12A6D4F7DB0","title":"Say How I Feel"}},{"artist":{"name":"Bessie Smith"},"song":{"id":"SOBWBGS12AB01868B0","title":"Cold In Hands Blues"}},{"artist":{"name":"Glen Campbell And Bobbie Gentry"},"song":{"id":"SOSXYJQ12A6D4FB699","title":"Mornin\u0027 Glory"}},{"artist":{"name":"Herbert Von Karajan"},"song":{"id":"SOUVYHS12A8C13AB77","title":"Die Fledermaus - Operette in drei Akten/Silvester-Einlagen/Dein ist mein ganzes Herz (aus \"Das Land des LA$?chelns\")"}},{"artist":{"name":"Gaiteros de Pillopo"},"song":{"id":"SOKAWBI12AB018277B","title":"El Barbero"}},{"artist":{"name":"Beatnuts featuring dead prez and Cheryl Pepsi Riley"},"song":{"id":"SOWNKEY12A8C131FE7","title":"Look Around featuring dead prez and Cheryl Pepsi Riley"}},{"artist":{"name":"The Sun Harbor\u0027s Chorus-Documentary Recordings"},"song":{"id":"SOEJGDS12A8C13875E","title":"America the Beautiful"}},{"artist":{"name":"Various Indian Tribes"},"song":{"id":"SOMFGBQ12A582917CD","title":"Mountain By The Sea (Tribe Unknown)"}},{"artist":{"name":"Anat Ben David"},"song":{"id":"SOKYSHY12A8C13EA99","title":"Moon Boom"}},{"artist":{"name":"Dexys Midnight Runners"},"song":{"id":"SOQTVUL12A6D4F8F04","title":"Until I Believe In My Soul"}},{"artist":{"name":"Blue October"},"song":{"id":"SOHOPAT12A8C1436AC","title":"My Never"}},{"artist":{"name":"X"},"song":{"id":"SOCKZDX12A58A7B950","title":"Motel Room In My Bed (LP Version)"}},{"artist":{"name":"Alain Morisod"},"song":{"id":"SORZRPC12A8C13A1B1","title":"Besame Mucho"}},{"artist":{"name":"David Meece"},"song":{"id":"SOSWXBF12A58A78B99","title":"Some People They Never Believe (LP Version)"}},{"artist":{"name":"Harvey Averne"},"song":{"id":"SOFMNYQ12AC468D899","title":"Why Can\u0027t We Really Be Free"}},{"artist":{"name":"Tyrone Taylor"},"song":{"id":"SOKAMAI12AB01852F5","title":"Members Only"}},{"artist":{"name":"Erik Berglund"},"song":{"id":"SOZYFSB12A8C1393CF","title":"All I Ask Of You"}},{"artist":{"name":"Beto Cuevas"},"song":{"id":"SOIKXDG12A8C13E7E1","title":"Mentira"}},{"artist":{"name":"Mississippi John Hurt"},"song":{"id":"SOGOHFY12A8C136F9C","title":"Waiting For You (I Forgive You Before I Go)"}},{"artist":{"name":"Gloria"},"song":{"id":"SOSCKDQ12A81C22BA4","title":"If Music Be The Food Of Love"}},{"artist":{"name":"The Fever"},"song":{"id":"SOHQPWP12A58A7986C","title":"Bye Bye Betty Blue"}},{"artist":{"name":"Vanessa Bell Armstrong"},"song":{"id":"SOVWHFZ12A8C14489D","title":"Greater"}},{"artist":{"name":"Ultimate Fakebook"},"song":{"id":"SONLCJU12A58A7B69C","title":"This Will Be Laughing Week"}},{"artist":{"name":"Between The Buried And Me"},"song":{"id":"SOIKALD12A81C231CB","title":"Foam Born (A) The Backtrack (Album Version)"}},{"artist":{"name":"Bert Kaempfert And His Orchestra"},"song":{"id":"SOKFCJJ12A67ADA72B","title":"Wheeling Free"}},{"artist":{"name":"Miossec"},"song":{"id":"SOYXFNV12AB0182DEA","title":"Nos plus belles annA(c)es"}},{"artist":{"name":"Rebecca Lynn Howard"},"song":{"id":"SOZOEYQ12A8C1406E3","title":"I\u0027m Over You (Album Version)"}},{"artist":{"name":"Virtuoso"},"song":{"id":"SOKENHI12A8C1420D3","title":"Beautiful Maria of My Soul"}},{"artist":{"name":"Karen Peck And New River"},"song":{"id":"SOJFRZB12A6D4F92E2","title":"Feels Good To Be Free"}},{"artist":{"name":"Mulberry Lane"},"song":{"id":"SOBDCSO12AB017F02D","title":"Come Dance With Me"}},{"artist":{"name":"GA1/4nter Noris"},"song":{"id":"SOGCCYM12A8AE4705B","title":"Was Machst Du Mit Dem Knie_ Lieber Hans?"}},{"artist":{"name":"The Lord Weird Slough Feg"},"song":{"id":"SOHQUTZ12AB0185F78","title":"Beast In the Broch"}},{"artist":{"name":"Ice Cube"},"song":{"id":"SOVLDMX12A8C141DB5","title":"When Will They Shoot? (Explicit)"}},{"artist":{"name":"Bert Kaempfert And His Orchestra"},"song":{"id":"SOBNOBG12A6D4FB54B","title":"Let\u0027s Go Home"}},{"artist":{"name":"Vincenzo Bellini"},"song":{"id":"SOBVMXR12A58A7AE67","title":"Bellini: Norma: Vanne_ e li cela entrambi"}},{"artist":{"name":"Theodor Zox"},"song":{"id":"SOFJEAL12A8C13E4C5","title":"What\u0027s in a number \u0026 Feed me lies remixes"}},{"artist":{"name":"Cake"},"song":{"id":"SOLUABP12AF72A2CD2","title":"Alpha Beta Parking Lot"}},{"artist":{"name":"Between The Buried And Me"},"song":{"id":"SOCKCXC12A6D4FD052","title":"Geek USA (Album Version)"}},{"artist":{"name":"BeyoncA(c)"},"song":{"id":"SORLLRN12A58A7F1EE","title":"Be With You"}},{"artist":{"name":"Headliners"},"song":{"id":"SOOTRFL12A6D4F5428","title":"Sag Ihnen Bescheid"}},{"artist":{"name":"Babe Ruth"},"song":{"id":"SOZIGEW12AB0183C28","title":"Dancer (2007 Digital Remaster)"}},{"artist":{"name":"Margaret Becker"},"song":{"id":"SOAZRCH12AB017A84D","title":"Start The Fire"}},{"artist":{"name":"Margaret Becker"},"song":{"id":"SOCLAFZ12AF72A6D7F","title":"Stay Close To Me"}},{"artist":{"name":"Jarvis Church"},"song":{"id":"SODMLAB12A8C1441D2","title":"So Beautiful"}},{"artist":{"name":"Fabolous"},"song":{"id":"SOGOJEP12AB018D355","title":"Ma\u0027 Be Easy [Explicit Version]"}},{"artist":{"name":"Ben E. King"},"song":{"id":"SOMDTTT12A8C13F1CB","title":"Let It Be Me"}},{"artist":{"name":"Cumberland Quartet"},"song":{"id":"SOTREAP12A8AE46FE2","title":"One Day At A Time"}},{"artist":{"name":"U2"},"song":{"id":"SOUATDY12AB0185157","title":"FEZ-Being Born"}},{"artist":{"name":"Tony Martin"},"song":{"id":"SOQQXOZ12AB01809E4","title":"September Song"}},{"artist":{"name":"Beres Hammond"},"song":{"id":"SONBWQQ12A58A7BF65","title":"Missing You For A Mile"}},{"artist":{"name":"Los Tres Diamantes"},"song":{"id":"SOMVRPL12A81C20EAC","title":"Begin The Beguine"}},{"artist":{"name":"Handsome Boy Modeling School"},"song":{"id":"SOEUEUI12A6701E4AB","title":"I\u0027ve Been Thinking featuring Cat Power (Album Version)"}},{"artist":{"name":"Bersuit Vergarabat"},"song":{"id":"SOHAVVY12A8C1422E6","title":"De Onda"}},{"artist":{"name":"Bedwetters"},"song":{"id":"SODLFHM12A8C1432E9","title":"Like A Deck Of Cards"}},{"artist":{"name":"Clarisse Lavanant"},"song":{"id":"SONBEXJ12AB0182AC8","title":"Beaux parleurs"}},{"artist":{"name":"BeauSoleil"},"song":{"id":"SOCJFFQ12A8C13E02A","title":"\u0027Ti Monde (LP Version)"}},{"artist":{"name":"The Dee Jays"},"song":{"id":"SOKPIYN12A8C13F84F","title":"Dum Dum (Marble Breaks And Iron Bends)"}},{"artist":{"name":"Brian Eno And David Byrne"},"song":{"id":"SOAGYNF12AB0187EEE","title":"The Jezebel Spirit"}},{"artist":{"name":"Herbert Von Karajan"},"song":{"id":"SOFNNDS12A8C138268","title":"Variations Sur Un Theme De Haydn Op51"}},{"artist":{"name":"Herbert Von Karajan"},"song":{"id":"SOHTCQC12A6D4F49CA","title":"Si Mi Chiamano Mimila Boheme Act1 Remast"}},{"artist":{"name":"Petra"},"song":{"id":"SOJDKQV12A6D4FAF0E","title":"Don\u0027t Let Your Heart Be Hardened (This Means War Album Version)"}},{"artist":{"name":"Jean-Yves Thibaudet / Gewandhausorchester Leipzig / Herbert Blomstedt"},"song":{"id":"SOLVUWT12A6D4FA589","title":"1. Molto allegro con fuoco"}},{"artist":{"name":"Lil Boosie"},"song":{"id":"SOQDCHV12A6D4FC12D","title":"I Remember (amended album version)"}},{"artist":{"name":"Dinosaur Jr."},"song":{"id":"SOZRIFJ12A67ADA4BE","title":"Been There All The Time"}},{"artist":{"name":"Autonomous Bass Heads"},"song":{"id":"SOHTPLG12AB0185DF3","title":"Beat Conductor"}},{"artist":{"name":"Alberto Cortez"},"song":{"id":"SOTWTSO12A8C142128","title":"Guitarra Dimelo Tu"}},{"artist":{"name":"Bill \u0026 Gloria Gaither"},"song":{"id":"SOKFQQD12A8C138826","title":"Jesus Hold My Hand (The Best of Homecoming - Volume 1 Version)"}},{"artist":{"name":"Patrick Lamb"},"song":{"id":"SOQVDWT12AC468A52B","title":"I Remember"}},{"artist":{"name":"Melvins"},"song":{"id":"SOAIQBP12AB01899F4","title":"You\u0027ve Never Been Right - (Live In Boston_ MA 2008)"}},{"artist":{"name":"Vivian"},"song":{"id":"SOVKZLE12AB018A2F4","title":"Better"}},{"artist":{"name":"Bescenta"},"song":{"id":"SOACIFE12AB0187C9C","title":"So In Love"}},{"artist":{"name":"Elmer Bernstein"},"song":{"id":"SOYIRYT12A6D4F9B3E","title":"Drown The Dog!"}},{"artist":{"name":"Neeme Jarvi"},"song":{"id":"SOILAOQ12AB01894C9","title":"Hary Janos Suite : VI. A csaszari udvar bevonulasa (Entrance of the Emperor and his Court)"}},{"artist":{"name":"Los Fabulosos Cadillacs"},"song":{"id":"SOSPNDI12AB017F769","title":"Noches Arabes"}},{"artist":{"name":"Lizzy Borden"},"song":{"id":"SOQHTSH12AB01849EE","title":"There Will Be Blood Tonight"}},{"artist":{"name":"Casual"},"song":{"id":"SODKPKO12A58A79DF7","title":"I believe"}},{"artist":{"name":"Bebo Norman"},"song":{"id":"SOEJCNS12A8C142BBE","title":"Borrow Mine"}},{"artist":{"name":"Isabel Pantoja"},"song":{"id":"SOFXDAO12A6D4FA140","title":"Limosna De Amores"}},{"artist":{"name":"Juanes"},"song":{"id":"SOBXWEW12AB017FB9B","title":"Rebelion"}},{"artist":{"name":"Staatskapelle Dresden/Herbert Blomstedt"},"song":{"id":"SOBFOYA12A6D4FB36C","title":"Peer Gynt - Incidental Music (2004 Digital Remaster): 4.   In the Hall of the Mountain King"}},{"artist":{"name":"Jeff Beck Group"},"song":{"id":"SOCXWVO12A58A7E7C6","title":"Jody"}},{"artist":{"name":"Ben E. King"},"song":{"id":"SOXAXWG12A81C20D97","title":"You Made The Difference To My Life (LP Version)"}},{"artist":{"name":"Bob Wills"},"song":{"id":"SOCBXDX12A8C13EE08","title":"Bubbles in My Beer"}},{"artist":{"name":"Dobet GnahorA(c)"},"song":{"id":"SOBYHEB12AB01877E6","title":"Wigue"}},{"artist":{"name":"Smidi Beats"},"song":{"id":"SOYUGSB12AB01865FA","title":"Grin\u0027in In Ya Face"}},{"artist":{"name":"Leon Russel"},"song":{"id":"SOTIXNQ12A58A77E78","title":"Three Bells / Les 3 cloches"}},{"artist":{"name":"JoAPSo Gilberto / Gilberto Gil / Caetano Veloso"},"song":{"id":"SOHUKWF12A6D4FA598","title":"Cordeiro De Nana"}},{"artist":{"name":"The Beatles"},"song":{"id":"SORTPSA12A67ADBFE2","title":"Derek Taylor - Introduction"}},{"artist":{"name":"Bellatrax feat. Tina Cousins"},"song":{"id":"SOCPFPB12AB018C6F6","title":"Can\u0027t Hold Back"}},{"artist":{"name":"Ice Cube"},"song":{"id":"SOHFJCZ12CF533CFBB","title":"Why We Thugs (edited version)"}},{"artist":{"name":"Sandy Posey"},"song":{"id":"SOCWCNX12AB0185027","title":"When Will I Be Loved"}},{"artist":{"name":"Ice Cube"},"song":{"id":"SOBHRGE12A8C13C81D","title":"Gangsta\u0027s Fairytale 2 (Explicit)"}},{"artist":{"name":"George Nooks"},"song":{"id":"SOEHRVB12A8C1324C3","title":"Better Way Of Life"}},{"artist":{"name":"Bela Fleck And The Flecktones"},"song":{"id":"SOPQUHV12A8C143FB2","title":"Frontiers (LP Version)"}},{"artist":{"name":"Bruce BecVar"},"song":{"id":"SOCCSCK12A58A7B859","title":"Razamataz"}},{"artist":{"name":"Between The Buried And Me"},"song":{"id":"SOUJQRS12A6D4F7ADE","title":"Use Of A Weapon (Album Version)"}},{"artist":{"name":"Mindy McCready"},"song":{"id":"SONIQTE12A58A7A189","title":"Be With Me"}},{"artist":{"name":"Pat Travers"},"song":{"id":"SOEQLVJ12AB0186D17","title":"Black Betty"}},{"artist":{"name":"Bobby Russell"},"song":{"id":"SOADLFU12A8C1393FD","title":"Jingle Bell Rock"}},{"artist":{"name":"The Jets \u0026 The Sharks \u0026 Leonard Bernstein\u0026The New York Philharmonic Orchestra"},"song":{"id":"SOPDIKM12AB017E911","title":"The Dance at The Gym"}},{"artist":{"name":"Buddy Johnson"},"song":{"id":"SORLQLI12A8C1373BB","title":"Because - Part 1"}},{"artist":{"name":"Andy \u0026 Lucas"},"song":{"id":"SOLLQHF12A8C13FC20","title":"Dios Bendiga"}},{"artist":{"name":"Kool Keith"},"song":{"id":"SONYMCA12AB0184228","title":"Wanna Be A Star"}},{"artist":{"name":"MichA\"le Bernard"},"song":{"id":"SOBVPZG12AC46862C6","title":"Le bar du grand dA(c)sir"}},{"artist":{"name":"A Tribe Called Quest"},"song":{"id":"SOIBEXL12A8AE46975","title":"Scenario"}},{"artist":{"name":"Jeff Beck Group"},"song":{"id":"SOCONYN12A8AE48117","title":"Ice Cream Cakes"}},{"artist":{"name":"Steve Smith"},"song":{"id":"SOHWKRB12AB017EB39","title":"Better Off That Way"}},{"artist":{"name":"Roberto Roena"},"song":{"id":"SOMNUEC12A8C13D9D3","title":"Oriza Eh"}},{"artist":{"name":"The Brooklyn Tabernacle Choir"},"song":{"id":"SOKHLYR12AF72A2F91","title":"Everything I Desire"}},{"artist":{"name":"King Curtis with Jack Dupree"},"song":{"id":"SODSHKO12A6D4FB716","title":"Everything\u0027s Gonna Be Alright (Live Version)"}},{"artist":{"name":"Orchestra e Coro del Palacio de Bellas Artes Di CittA! del Messico_ Oliviero De Fabritiis_ Maria Call"},"song":{"id":"SOBOFKI12A8C134832","title":"Atto Quarto: \u0027La Fatal Pietra Sovra Me Si Chiuse...\u0027 (Radames) (Verdi)"}},{"artist":{"name":"Margaret Becker"},"song":{"id":"SOEKCXN12A8C13FF8C","title":"Look Me In The Eye"}},{"artist":{"name":"Ron Goodwin"},"song":{"id":"SOPHRUQ12A6D4FAE96","title":"The Lull Before The Storm"}},{"artist":{"name":"Hatebreed (int License)"},"song":{"id":"SOEVAMO12AC90716AD","title":"Between Hell and A Heartbeat [Explicit]"}},{"artist":{"name":"Orquesta AragA3n"},"song":{"id":"SONPLPJ12AC4685296","title":"Mambo del Beso"}},{"artist":{"name":"Timo Maas"},"song":{"id":"SOADCCE12A6D4FA324","title":"UBIK The Breakz (feat. Martin Bettinghaus) - Radio Mix"}},{"artist":{"name":"Heavenly"},"song":{"id":"SOOFHNG12A6D4FAB3A","title":"Liberty"}},{"artist":{"name":"Yuko Kanzaki"},"song":{"id":"SOKPFAL12AC90979AB","title":"Seikurabe (Karaoke)"}},{"artist":{"name":"Eminem"},"song":{"id":"SOZYRBU12AB0181196","title":"Beautiful"}},{"artist":{"name":"Simply Red"},"song":{"id":"SOFLHAS12A8C13851C","title":"Maybe Someday..."}},{"artist":{"name":"BA(c)zu"},"song":{"id":"SORYMFO12AB0185343","title":"Le clair de lune A  maubeuge"}},{"artist":{"name":"Robben Ford"},"song":{"id":"SODVGUA12AB017D708","title":"Spoonful"}},{"artist":{"name":"Beherit"},"song":{"id":"SOYEWDH12AAF3B45CE","title":"Werewolf_ Semen And Blood"}},{"artist":{"name":"SNAP!"},"song":{"id":"SOFWOXM12A67ADEA89","title":"Beauty Queen (12\" Spoon Club Mix)"}},{"artist":{"name":"Marco Beltrami"},"song":{"id":"SOIKWWB12AAF3B45D0","title":"Revelations"}},{"artist":{"name":"Elizabeth Cotten"},"song":{"id":"SOJURPV12A8C141B82","title":"Freight Train"}},{"artist":{"name":"Tommy McLain"},"song":{"id":"SOUKTVZ12AB017E93B","title":"Let It Be Me"}},{"artist":{"name":"Cece Winans"},"song":{"id":"SOJOAOZ12A58A7D7B6","title":"Because Of You"}},{"artist":{"name":"Robert Palmer"},"song":{"id":"SOJCYES12A6D4F78AE","title":"Love Can Run Faster"}},{"artist":{"name":"Sergio Franchi"},"song":{"id":"SOKZCJZ12A8C13972F","title":"Oh Little Town Of Bethlehem"}},{"artist":{"name":"Janet Paschal"},"song":{"id":"SOMXCXZ12A58A7B343","title":"The Lord Will Go Before You"}},{"artist":{"name":"Coffinberry"},"song":{"id":"SOWGAUD12A58A76907","title":"Welcome To Hell"}},{"artist":{"name":"Young-Holt Unlimited"},"song":{"id":"SOLGASB12A58A79460","title":"We\u0027ve Only Just Begun (LP Version)"}},{"artist":{"name":"Brenda Boykin"},"song":{"id":"SOXIBUG12AB018914B","title":"Be My Lover"}},{"artist":{"name":"Erik Berglund"},"song":{"id":"SOPEYTA12A8C1352AB","title":"Angel Of Heaven\u0027s Gate"}},{"artist":{"name":"Roger Reynolds"},"song":{"id":"SOSZOXP12A6D4FB9A9","title":"Binaural Presentation - Focus On A Beam Emptied Of Thinking_ Outward..."}},{"artist":{"name":"Jim Reeves"},"song":{"id":"SOPQNUE12A8C13DB5A","title":"I\u0027d Like To Be"}},{"artist":{"name":"Luke Vibert"},"song":{"id":"SOZTOSX12AC468AD34","title":"Mate Tron"}},{"artist":{"name":"Lifehouse"},"song":{"id":"SOQLWQU12A8C13C87E","title":"Better Luck Next Time"}},{"artist":{"name":"Don Campbell"},"song":{"id":"SOUQYAU12AB0181058","title":"Unchain Us"}},{"artist":{"name":"Bert Kaempfert"},"song":{"id":"SOZFJLR12A6D4FB512","title":"Don\u0027t Go"}},{"artist":{"name":"Beenie Man Featuring Janet Jackson"},"song":{"id":"SOBGXEU12A8AE45903","title":"Feel It Boy (Deep Dish Danchall Remix) (Feat. Janet Jackson)"}},{"artist":{"name":"Danny Wilson"},"song":{"id":"SOCUSNQ12A8C138A86","title":"Never Gonna Be The Same"}},{"artist":{"name":"Malefaction"},"song":{"id":"SOABPYH12A8C13CC48","title":"Beothuck"}},{"artist":{"name":"Baby D"},"song":{"id":"SOIAJRZ12A8C136212","title":"Let Me Be Your Fantasy"}},{"artist":{"name":"Juelz Santana / Bezel"},"song":{"id":"SOQDEXL12A6D4F7004","title":"Violence"}},{"artist":{"name":"Paul Glazby"},"song":{"id":"SOYETRS12AB018A8F2","title":"Beautiful"}},{"artist":{"name":"White Heart"},"song":{"id":"SOVAPNH12A8AE46E05","title":"Nothing But The Best"}},{"artist":{"name":"Saga"},"song":{"id":"SOQQHZK12A8C144617","title":"Believe"}},{"artist":{"name":"Salt The Wound"},"song":{"id":"SOVKFKF12A8C14348A","title":"The Beginning"}},{"artist":{"name":"Bert Kaempfert"},"song":{"id":"SONBIEL12AB018234B","title":"Cha Cha Brasilia"}},{"artist":{"name":"Richard Lloyd"},"song":{"id":"SOMRDBW12A6D4F9F07","title":"Number Nine (LP Version)"}},{"artist":{"name":"Charlie Khan"},"song":{"id":"SOXCEGC12AB018A0BD","title":"Beautiful When You\u0027re Green"}},{"artist":{"name":"BeyoncA(c)"},"song":{"id":"SOYNBBT12A8AE46457","title":"Irreplaceable (Irreemplazable)"}},{"artist":{"name":"Beenie Man"},"song":{"id":"SOKJCDI12A81C22EB0","title":"Imagination"}},{"artist":{"name":"Be Bop Deluxe"},"song":{"id":"SOTAEIP12A6D4F76A5","title":"Between The Worlds"}},{"artist":{"name":"BeyoncA(c)"},"song":{"id":"SOYVXRJ12AB017CDD6","title":"Ring The Alarm"}},{"artist":{"name":"J Bostron \u0026 Beretta"},"song":{"id":"SOOEQOD12AB018D7D3","title":"Now U Got It"}},{"artist":{"name":"Mark Ashley"},"song":{"id":"SOMPBTH12A8AE48A8B","title":"I\u0027ve never been so Lonely"}},{"artist":{"name":"Eberhard Weber"},"song":{"id":"SOYCYFG12A81C22BA1","title":"Unfinished Self-Portrait"}},{"artist":{"name":"Tesla"},"song":{"id":"SOUROPB12A6D4FAC51","title":"Gettin\u0027 Better"}},{"artist":{"name":"The Field Mice"},"song":{"id":"SOQPENF12A8C13D7D8","title":"Below The Stars"}},{"artist":{"name":"Billy Higgins_ Bob Berg_ Cedar Walton_ Tony Dumas"},"song":{"id":"SOOYXSC12A8AE47FDF","title":"Plexis"}},{"artist":{"name":"The Cate Brothers"},"song":{"id":"SOFTSMC12AB017C6BD","title":"Let It Be"}},{"artist":{"name":"Johannes Linstead"},"song":{"id":"SOAVMSM12AB017CC5C","title":"Guayabera"}},{"artist":{"name":"Otis Spann"},"song":{"id":"SOEWHWK12A8C14264E","title":"Must Have Been The Devil"}},{"artist":{"name":"Anat Ben David"},"song":{"id":"SOCYTYU12A8C13EA94","title":"Robot Kid"}},{"artist":{"name":"Robben Ford"},"song":{"id":"SOBEZJB12A6D4FBA4A","title":"The Champ"}},{"artist":{"name":"Sean Callery"},"song":{"id":"SOOBSJA12AAA8C7724","title":"Jack and Benton"}},{"artist":{"name":"Scott Glasgow"},"song":{"id":"SOLGYJO12A6BD55664","title":"Space Station Liberty"}},{"artist":{"name":"Amy Lambert"},"song":{"id":"SOWJXCF12A8C13608D","title":"Because He Loves Me"}},{"artist":{"name":"Rise Against"},"song":{"id":"SOKSSEC12AF72A3D89","title":"Intro/Chamber The Cartridge"}},{"artist":{"name":"Gaetano Donizetti"},"song":{"id":"SOQANLU12A8C142FEF","title":"Donizetti: Roberto Devereux: Ah! Ritorna qual ti spero...."}},{"artist":{"name":"Teenage Fanclub"},"song":{"id":"SOPLZYS12A8AE48DE6","title":"The World\u0027ll Be OK"}},{"artist":{"name":"Hatebreed (int License)"},"song":{"id":"SOYWICF12A8C13BDD7","title":"Beholder of Justice (Album Version)"}},{"artist":{"name":"Snowgoons"},"song":{"id":"SOIBTMP12AF729FC8F","title":"Been Fighting Devilz"}},{"artist":{"name":"Jah Legacy"},"song":{"id":"SOGACHN12AB0187ACA","title":"What is the best"}},{"artist":{"name":"Margaret Becker"},"song":{"id":"SOCRJDM12A8C139311","title":"Cave It In"}},{"artist":{"name":"Isabel Pantoja"},"song":{"id":"SOHRBUD12A8C13A769","title":"Porque Me Gusta A Morir"}},{"artist":{"name":"MichA\"le Bernard"},"song":{"id":"SOJUIEW12AC468957F","title":"Monsieur qui s\u0027engraisse"}},{"artist":{"name":"Helen Love"},"song":{"id":"SOBSOLH12A58A7E673","title":"Atomic Beat Boy (Album Version)"}},{"artist":{"name":"2raumwohnung"},"song":{"id":"SOJYNQE12AB0186EAB","title":"Rette Mich SpA$?ter (Michael Ilbert Radio Mix)"}},{"artist":{"name":"Porcupine Tree"},"song":{"id":"SONJMCI12AB018B16A","title":"Remember Me Lover (Album Version)"}},{"artist":{"name":"DAVE MATTHEWS BAND"},"song":{"id":"SOQLLHX12AF72A3586","title":"The Space Between"}},{"artist":{"name":"John Berry"},"song":{"id":"SOKDGEX12A6D4F6537","title":"She\u0027s Taken A Shine"}},{"artist":{"name":"Frederick Knight"},"song":{"id":"SOHOXPI12A81C21566","title":"I\u0027ve Been Lonely (For So Long)"}},{"artist":{"name":"Mario Rosenstock"},"song":{"id":"SOJONVF12AB01866C3","title":"The Best Of Radio Roy 1 (Best of 2009)"}},{"artist":{"name":"Fehlfarben"},"song":{"id":"SOJXNPU12A8C13170B","title":"Magnificent Obsession"}},{"artist":{"name":"Albert PrA(c)jean"},"song":{"id":"SOMBYVD12AB01884BE","title":"Dede De Montmartre"}},{"artist":{"name":"Amber Nicholson"},"song":{"id":"SOJEUHQ12A6D4FC92D","title":"Tonight It\u0027s Just Me"}},{"artist":{"name":"Bessie Smith"},"song":{"id":"SOBHLPN12AB01822EB","title":"Gin House Blues"}},{"artist":{"name":"Los Rumberos Catalanes"},"song":{"id":"SOXPCVS12A8AE4892F","title":"Yo Te Camelo"}},{"artist":{"name":"Paulo Flores"},"song":{"id":"SOZJZQG12AB01828BD","title":"Belina"}},{"artist":{"name":"Jerry Butler"},"song":{"id":"SOIJTGT12AB017D995","title":"Let It Be Me(with Betty Everrett)"}},{"artist":{"name":"Eason Chan"},"song":{"id":"SOCGBAY12AB017C78E","title":"Been Sick Lung"}},{"artist":{"name":"Abbott \u0026 Chambers"},"song":{"id":"SOTJXRK12AAF3B264E","title":"Where Are You"}},{"artist":{"name":"Peggy Lee"},"song":{"id":"SOOAHQO12A6D4FA507","title":"If You Build A Better Mousetrap"}},{"artist":{"name":"Lightnin\u0027 Slim"},"song":{"id":"SOEXZJD12AB0182FC1","title":"My Babe"}},{"artist":{"name":"Dora The Explorer"},"song":{"id":"SOFTAZM12A8C141CD9","title":"ABC (The Alphabet Song)"}},{"artist":{"name":"Ben Sidran"},"song":{"id":"SONIMPI12AB0186C14","title":"See You On The Other Side"}},{"artist":{"name":"Long Beach Dub Allstars"},"song":{"id":"SOCXKCF12AF729F898","title":"Kablammin\u0027 It"}},{"artist":{"name":"Beastie Boys"},"song":{"id":"SOJHMFW12B0B80B79B","title":"Shadrach"}},{"artist":{"name":"John Berry"},"song":{"id":"SOJXOVT12AB018581C","title":"Let\u0027s Fall In Love This Christmas"}},{"artist":{"name":"Moving Ninja"},"song":{"id":"SOXXSLE12AB0184F1B","title":"Lost Tribe"}},{"artist":{"name":"Beto y sus Canarios"},"song":{"id":"SOAJTFZ12AB0186524","title":"Noche Eterna"}},{"artist":{"name":"Robin Fox"},"song":{"id":"SOMZLIQ12A8C13BA38","title":"It\u0027s Gonna Be Okay (Original Mix)"}},{"artist":{"name":"Seal"},"song":{"id":"SOCSOYD12A8C13AF1B","title":"The Beginning (Giro E Giro Mix)"}},{"artist":{"name":"La BergA\"re"},"song":{"id":"SOXQTLK12AB018A1D9","title":"(Et puis) Elle allait"}},{"artist":{"name":"Janet Paschal"},"song":{"id":"SOJYNKH12A8C13A0D6","title":"Take This Trail Trip Beside Me (The Best Of Janet Paschal)"}},{"artist":{"name":"Frank Chacksfield"},"song":{"id":"SOUOVZX12AB018A15C","title":"Beginner\u0027s Luck"}},{"artist":{"name":"Jimmy Witherspoon"},"song":{"id":"SOELNXC12A58A7AFD5","title":"Better Love Next Time Part 2"}},{"artist":{"name":"R. Carlos Nakai"},"song":{"id":"SOWTJTU12AB0183CBB","title":"Tibetan Turquoise (World)"}},{"artist":{"name":"Kieran"},"song":{"id":"SOLTZTZ12A58A7A84F","title":"Best Friends"}},{"artist":{"name":"CA(c)line Dion"},"song":{"id":"SOOTADG12AF729F5CF","title":"Because You Loved Me (Theme from \"Up Close and Personal\")"}},{"artist":{"name":"Kitty Wells"},"song":{"id":"SOKNYLI12AB018846C","title":"Makin\u0027 Believe"}},{"artist":{"name":"Isabel Pantoja"},"song":{"id":"SOJHEMH12A8C13D4B2","title":"Adelante"}},{"artist":{"name":"Beastie Boys"},"song":{"id":"SOBTDFV12B0B80B789","title":"Get It Together"}},{"artist":{"name":"Beatnuts"},"song":{"id":"SOPFPTM12A8C135D00","title":"No Escapin\u0027 This"}},{"artist":{"name":"Nicola Fasano"},"song":{"id":"SOBSFSK12AC468926B","title":"Been a Long Time (feat. Paula B) [Club Radio]"}},{"artist":{"name":"Richie McDonald"},"song":{"id":"SOVKHLV12AB0187078","title":"If Every Day Could Be Christmas"}},{"artist":{"name":"Smash Palace"},"song":{"id":"SOJDTLW12A8C1394FD","title":"It\u0027s All Because"}},{"artist":{"name":"Fehlfarben"},"song":{"id":"SOXNQKW12A6701F7E0","title":"The Tarnished Angels (remastered)"}},{"artist":{"name":"Juana Molina"},"song":{"id":"SONQKDG12A8C130D96","title":"Isabel"}},{"artist":{"name":"Reginaldo Bessa"},"song":{"id":"SOYYUBG12AB01853E2","title":"O Smaba Que Eu NAPSo Fiz"}},{"artist":{"name":"Bersuit Vergarabat"},"song":{"id":"SOHDNUO12AB0183EC1","title":"Bolivian Surf"}},{"artist":{"name":"Cracker"},"song":{"id":"SOPWGTF12A58A7D658","title":"Dr. Bernice"}},{"artist":{"name":"Cheri Keaggy"},"song":{"id":"SOJMGIE12A8C137C14","title":"The Cross That Bears His Name"}},{"artist":{"name":"JoAPSo Gilberto"},"song":{"id":"SOOVQIU12A6D4FB6C9","title":"Meditacao"}},{"artist":{"name":"Eduardo Fernandez / Norbert Blume / English Chamber Orchestra / George Malcolm"},"song":{"id":"SOPRXCY12AB0183788","title":"1. Allegro"}},{"artist":{"name":"Smidi Beats"},"song":{"id":"SORQGPC12AB01859EA","title":"All Shook Up"}},{"artist":{"name":"The Robert Cray Band"},"song":{"id":"SOYACRZ12A6D4FA356","title":"Bad Influence"}},{"artist":{"name":"Abbott \u0026 Chambers"},"song":{"id":"SOLIERS12A58A75718","title":"Where Are You"}},{"artist":{"name":"Starski and Clutch"},"song":{"id":"SOCPVQM12AB0184ABB","title":"Belle Isle Players"}},{"artist":{"name":"Simon \u0026 Garfunkel"},"song":{"id":"SODTEMK12AF72A7210","title":"A Simple Desultory Philippic (Or How I Was Robert McNamara\u0027d Into Submission)"}},{"artist":{"name":"Professor Longhair"},"song":{"id":"SONDTMH12AC468965E","title":"No Buts - No Maybes"}},{"artist":{"name":"Erik Berglund"},"song":{"id":"SOYZBUV12A8C1393FD","title":"Ave Maria"}},{"artist":{"name":"Patti Smith"},"song":{"id":"SOMHYKZ12B34F1F013","title":"Lo and Beholden"}},{"artist":{"name":"Grizzly Bear"},"song":{"id":"SOLLOTO12AB01804C6","title":"Deep Blue Sea (Daniel Rossen home recording)"}},{"artist":{"name":"Emperor"},"song":{"id":"SONHKXA12AB0180478","title":"In the Wordless Chamber"}},{"artist":{"name":"Akon / Kardinal Offishall"},"song":{"id":"SOCEHMD12A67AD94C4","title":"Belly Dancer (Bananza) Remix ft. Kardinal Offishall"}},{"artist":{"name":"BerrogA1/4etto"},"song":{"id":"SOGDLRA12AC468F00B","title":"Navicularia"}},{"artist":{"name":"JosA(c) Roberto Bertrami"},"song":{"id":"SOCYSYD12AAF3B2F7B","title":"Sheds And Weeds (Barracos E Arbustos)"}},{"artist":{"name":"Belle and Sebastian"},"song":{"id":"SOBWVGX12AB017BD87","title":"Like Dylan In The Movies"}},{"artist":{"name":"Behemoth"},"song":{"id":"SOSVBAP12A58A7ABC2","title":"No Sympathy For Fools"}},{"artist":{"name":"Ministry of Sound"},"song":{"id":"SOFDJER12A6D4FD361","title":"Bitesize - Electro Beats Mix"}},{"artist":{"name":"Madonna"},"song":{"id":"SOCYUZL12A6701FA23","title":"Bedtime Story (Album Version)"}},{"artist":{"name":"JoAPSo Gilberto"},"song":{"id":"SOHBPQS12A58A7A631","title":"Eu E Meu Coracao"}},{"artist":{"name":"Byron Cage featuring Tye Tribbett"},"song":{"id":"SOGBFJS12AB0183AB7","title":"In The Midst"}},{"artist":{"name":"Albert King"},"song":{"id":"SODPBUM12A8C142299","title":"I\u0027m Gonna Move To The Outskirts Of Town - Live"}},{"artist":{"name":"Frankie Negron"},"song":{"id":"SOHKXIB12A81C207F1","title":"Comerte A Besos (Bachata Version)"}},{"artist":{"name":"Justin Timberlake"},"song":{"id":"SOALBQW12A8C142359","title":"What Goes Around...Comes Around"}},{"artist":{"name":"Scalplock"},"song":{"id":"SOJABTU12A58A7E1CA","title":"Safe in Numbers (Album Version)"}},{"artist":{"name":"Behemoth"},"song":{"id":"SODWVNV12A8C1423C6","title":"He Who Breeds Pestilence"}},{"artist":{"name":"Klubbingman feat. Beatrix Delgado"},"song":{"id":"SOAPRLL12AB0183EF2","title":"Another Day Another Night"}},{"artist":{"name":"Robert Palmer"},"song":{"id":"SOFLKHX12A6701C32A","title":"Looking For Clues"}},{"artist":{"name":"Oesch\u0027s die Dritten"},"song":{"id":"SOPXOYP12AB01883DE","title":"Die berA1/4ehmte drA1/4 WAPrtli"}},{"artist":{"name":"Mario Rosenstock"},"song":{"id":"SOMXQEF12AB0181AF0","title":"Obama\u0027s Election (Best of 2009)"}},{"artist":{"name":"Delbert McClinton"},"song":{"id":"SOGPXXQ12AB0180CC6","title":"He Will Break Your Heart"}},{"artist":{"name":"Beenie Man"},"song":{"id":"SOJIMUS12AB0181194","title":"Once a Year"}},{"artist":{"name":"Ben Jelen"},"song":{"id":"SOKWYNX12A58A802A6","title":"Wicked Little Town (Album Version)"}},{"artist":{"name":"Twila Paris"},"song":{"id":"SOJEBLF12A8C138B50","title":"How Beautiful (Cry For The Desert Album Version)"}},{"artist":{"name":"Ben E. King"},"song":{"id":"SOEUZAC12AB018C2B0","title":"Love Is Gonna Get You"}},{"artist":{"name":"Jeanne Robertson"},"song":{"id":"SOCZYSK12A8C135DB0","title":"Mumbling or hearing loss?"}},{"artist":{"name":"Albert King"},"song":{"id":"SOKQUFP12A8C140A16","title":"Watermelon Man"}},{"artist":{"name":"Nicola Fasano Feat. Paula B"},"song":{"id":"SOPOJXE12A6D4FA9BA","title":"Missing (Olivier Berger Mix)"}},{"artist":{"name":"Phil Collins"},"song":{"id":"SOJRFYT12A6D4F9972","title":"I Cannot Believe It\u0027s True"}},{"artist":{"name":"Rickie Lee Jones"},"song":{"id":"SOHJXOB12AB018627B","title":"It Must Be Love (Live Acoustic Version)"}},{"artist":{"name":"The Hokum Boys"},"song":{"id":"SOJFDTQ12A8C140F90","title":"Ain\u0027t Goin\u0027 To Beg You For That Stuff"}},{"artist":{"name":"Beres Hammond"},"song":{"id":"SOEEAEI12A8C1465B4","title":"Tender Lies"}},{"artist":{"name":"Beherit"},"song":{"id":"SOAHAZZ12AAF3B464A","title":"Lord of Shadows and Golden Wood"}},{"artist":{"name":"Tyrone Taylor"},"song":{"id":"SOGTZDE12AB017E44A","title":"I\u0027m A Believer"}},{"artist":{"name":"Ray Barretto"},"song":{"id":"SOQTZWV12A6D4F9D54","title":"Vaya (Live At The Beacon Theatre)"}},{"artist":{"name":"Quinteto Violado"},"song":{"id":"SOKATUR12A6D4FA32D","title":"Galope A Beira Mar"}},{"artist":{"name":"The Berzerker"},"song":{"id":"SOGFXKP12AB0180E00","title":"Humanity"}},{"artist":{"name":"Luke Vibert"},"song":{"id":"SOKJRSY12A58A7AA78","title":"Gwithian"}},{"artist":{"name":"Isabel Pantoja"},"song":{"id":"SOHQXIF12A8C13FEAD","title":"Si Tu Me Dices Ven"}},{"artist":{"name":"Beastie Boys"},"song":{"id":"SOCLHYJ12AB01820D4","title":"Shadrach (2009 Digital Remaster)"}},{"artist":{"name":"Shifty"},"song":{"id":"SOFKYTG12A6D4F7275","title":"EZ Cuz You\u0027re Beautiful (Album Version)"}},{"artist":{"name":"Glen Campbell"},"song":{"id":"SODMTUR12A8C13C8A4","title":"Woodcarver"}},{"artist":{"name":"Lil Boosie feat. Bun B_ Trae_ Yo Gotti \u0026 Foxx"},"song":{"id":"SOQHGND12AB018C00F","title":"Better Believe It Remix (feat. Bun B_ Trae_ Yo Gotti \u0026 Foxx)"}},{"artist":{"name":"ZombieSuckers"},"song":{"id":"SODHOGM12AB018A4FA","title":"The Nightmare Begins"}},{"artist":{"name":"Albert Ayler"},"song":{"id":"SONGCRV12AC468AE46","title":"Music Is The Healing Force Of The Universe"}},{"artist":{"name":"Becoming The Archetype"},"song":{"id":"SOBREKP12AB017DD9B","title":"End Of The Age"}},{"artist":{"name":"Beherit"},"song":{"id":"SOMWELJ12AB0184C6D","title":"Witchcraft"}},{"artist":{"name":"Rooney"},"song":{"id":"SOQSIIB12A6D4FBEFA","title":"Jump In My Bed"}},{"artist":{"name":"Ben Harper And The Blind Boys Of Alabama"},"song":{"id":"SOZOKIL12A6701EE9B","title":"Take My Hand"}},{"artist":{"name":"Clarence Fountain"},"song":{"id":"SOPMGXS12A8C133199","title":"Beams Of Heaven"}},{"artist":{"name":"Eurythmics"},"song":{"id":"SOQEBKX12A8C140A0F","title":"Better To Have Lost In Love (Than Never To Have Loved)"}},{"artist":{"name":"Champion Jack Dupree"},"song":{"id":"SOIRJHK12A67020A7B","title":"One Scotch_ One Bourbon_ One Beer"}},{"artist":{"name":"Rui Da Silva"},"song":{"id":"SOGPTDY12AB01890BE","title":"On My Mind (feat. Ben Onono) (The Drill-Re-Work Dub)"}},{"artist":{"name":"Beastie Boys"},"song":{"id":"SOHYDPA12B0B80B77C","title":"Eugene\u0027s Lament"}},{"artist":{"name":"Beogradski Sindikat"},"song":{"id":"SOKFHZG12AB0183FE5","title":"Plejersko ponasanje"}},{"artist":{"name":"Bomb Squad"},"song":{"id":"SOIFUXC12AB0182A9B","title":"Never Be (Bonus Track)"}},{"artist":{"name":"Barbara Lynn"},"song":{"id":"SODCVNW12AB0183A41","title":"It Ain\u0019t No Good To be Good "}},{"artist":{"name":"Beat Pharmacy"},"song":{"id":"SOYWXNN12AB018AC20","title":"Floating (Edit)"}},{"artist":{"name":"Tiny Tim"},"song":{"id":"SOJSJTR12AB0188131","title":"Stay Down Here Where You Belong"}},{"artist":{"name":"Mind Furniture"},"song":{"id":"SOQQUFP12AB0189123","title":"Hoop of Flame (III. Between Two Worlds)"}},{"artist":{"name":"The Baltimore Consort"},"song":{"id":"SOMLMRZ12AB017D510","title":"The Beautiful Shepherdess of Arcadia"}},{"artist":{"name":"Sivuca \u0026 ClAPS Brasil"},"song":{"id":"SOEHQMQ12AB01806CC","title":"Visitando ZabelAa"}},{"artist":{"name":"US Coast Guard Band"},"song":{"id":"SOMTHWO12A58A78109","title":"America The Beautiful"}},{"artist":{"name":"Isabel Pantoja"},"song":{"id":"SOCUAPA12A8C13FE6B","title":"13 De Mayo"}},{"artist":{"name":"Angelo Badalamenti"},"song":{"id":"SOBHMPJ12AB01899FE","title":"Vera Begs Dylan"}},{"artist":{"name":"Bert Kaempfert And His Orchestra"},"song":{"id":"SODTNTM12A6D4F98CB","title":"Games People Play"}},{"artist":{"name":"All Shall Persih"},"song":{"id":"SOGNSLP12A6D4FD729","title":"The True Beast"}},{"artist":{"name":"John Digweed"},"song":{"id":"SONNTQH12AB018C2D8","title":"Warung Beach"}},{"artist":{"name":"Vanessa Bell Armstrong"},"song":{"id":"SOMYGJH12A8C14114C","title":"Wonderful One"}},{"artist":{"name":"Adalberto Santiago"},"song":{"id":"SOWKWKH12A8C13C972","title":"Tu Me Desesperas"}},{"artist":{"name":"Johnny Winter"},"song":{"id":"SOGHYGL12A8C134B40","title":"Be Careful With A Fool"}},{"artist":{"name":"Jacques Douai"},"song":{"id":"SOENOKK12AB018642B","title":"Mes Belles Amourettes"}},{"artist":{"name":"Enslavement Of Beauty"},"song":{"id":"SOJZWRA12AB018D029","title":"And Still I Wither"}},{"artist":{"name":"David Raksin"},"song":{"id":"SOLSWAC12AAF3B5258","title":"The Bad And The Beautiful"}},{"artist":{"name":"Capone-N-Noreaga"},"song":{"id":"SOZTGFX12AB0181283","title":"Beef"}},{"artist":{"name":"BeyoncA(c)"},"song":{"id":"SOFQBMN12A8C1428AD","title":"Single Ladies (Put A Ring On It)"}},{"artist":{"name":"Robben Ford"},"song":{"id":"SOISSKN12AB01888AF","title":"Ain\u0027t Got Nothin\u0027 But The Blues (Album Version)"}},{"artist":{"name":"Belle and Sebastian"},"song":{"id":"SOEEESC12AB01835B1","title":"I Could Be Dreaming"}},{"artist":{"name":"Laurie Berkner"},"song":{"id":"SODXFCU12A58A78087","title":"ABCD Medley"}},{"artist":{"name":"Frank Stokes"},"song":{"id":"SOZKCNZ12A6D4FCAA3","title":"It Won\u0027t Be Long Now"}},{"artist":{"name":"The Steeles"},"song":{"id":"SOOLZNN12A8AE47E47","title":"Left Behind"}},{"artist":{"name":"Jeff Beck"},"song":{"id":"SOPKWKW12A8C1312BC","title":"Head For Backstage Pass"}},{"artist":{"name":"Crystals"},"song":{"id":"SOVBLWJ12A6D4F6EE4","title":"He\u0027s A Rebel"}},{"artist":{"name":"Bebe Winans / Stephanie Mills"},"song":{"id":"SOXVCSA12A8C137504","title":"Everyday"}},{"artist":{"name":"Three 6 Mafia"},"song":{"id":"SOXPAAZ12A8C13F495","title":"Let\u0027s Plan A Robbery"}},{"artist":{"name":"Behemoth"},"song":{"id":"SOYPZAE12A81C1FDC3","title":"Chant For Eschaton 2000"}},{"artist":{"name":"The Real Kids"},"song":{"id":"SOJKXAO12A58A7CB4F","title":"Better Be Good"}},{"artist":{"name":"MichA\"le Bernard"},"song":{"id":"SOORZRU12AC468A12D","title":"Chanson sous la pluie"}},{"artist":{"name":"BeyoncA(c)"},"song":{"id":"SOXTCSF12A8AE4628A","title":"Ring The Alarm"}},{"artist":{"name":"Spectra Soul"},"song":{"id":"SOQUEQP12A8C1397DE","title":"The Tube"}},{"artist":{"name":"Groucho Marx"},"song":{"id":"SOKHNPX12A8C14512E","title":"Show Fifteen with Bernard Sampson \u0026 Robert Sewell"}},{"artist":{"name":"California Oranges"},"song":{"id":"SOAGAFW12AB0181E97","title":"Feel Better"}},{"artist":{"name":"The Berzerker"},"song":{"id":"SOQWQSK12AB0180210","title":"Compromise"}},{"artist":{"name":"The Game feat. Jim Jones Camron \u0026 Bezell"},"song":{"id":"SOAEQKJ12A58A761EA","title":"Certified Gangstas (featuring Jim Jones Camron \u0026 Bezell)"}},{"artist":{"name":"Petra"},"song":{"id":"SOHYKZG12A6D4FAF0A","title":"Hollow Eyes (Beat The System Album Version)"}},{"artist":{"name":"Band Of Horses"},"song":{"id":"SONNELS12AB018048F","title":"Plans (Cover Version - Original by Grizzly Bear)"}},{"artist":{"name":"Edmundo Ros"},"song":{"id":"SOGXXTV12AB018B61D","title":"Happy Beat"}},{"artist":{"name":"The Strokes"},"song":{"id":"SOYINSW12B0B80BEBD","title":"Between Love \u0026 Hate"}},{"artist":{"name":"New Roanoke Jug Band"},"song":{"id":"SOPOEHR12A8C13D801","title":"I\u0027ve Been Cryin\u0027 Since You\u0027ve Been Gone"}},{"artist":{"name":"Luis Alberto Spinetta"},"song":{"id":"SOBBCFN12A8C13E4D9","title":"Llama y VerA!s"}},{"artist":{"name":"Stephen Warbeck"},"song":{"id":"SOLCSWD12A6D4FA136","title":"Birth Of The Falls"}},{"artist":{"name":"Harry Lauder"},"song":{"id":"SOQQPAX12AB0185375","title":"Portobello Lass"}},{"artist":{"name":"Kenny Rogers"},"song":{"id":"SONARPL12CF5465254","title":"Reuben James"}},{"artist":{"name":"Pelle Carlberg"},"song":{"id":"SOLEFXD12AC3DFA062","title":"Clever Girls Like Clever Boys Much More Than Clever Boys Like Clever Girls"}},{"artist":{"name":"Albert Collins"},"song":{"id":"SOWISQE12A6D4F7DBB","title":"Same Old Thing"}},{"artist":{"name":"Belami"},"song":{"id":"SODCJNH12AB018A3A9","title":"Te Miattad VA!ltozott Meg Az Aletem"}},{"artist":{"name":"The Marx Brothers"},"song":{"id":"SOJVAAE12A8BED74B1","title":"You Must Do Your Best Tonight / I Represent/Animal Crackers"}},{"artist":{"name":"Carl Belew"},"song":{"id":"SONZYRS12A8C141A13","title":"Am I That Easy To Forget"}},{"artist":{"name":"Grizzly Bear"},"song":{"id":"SOXDMAC12AB017E7FF","title":"Little Brother"}},{"artist":{"name":"Seatrain"},"song":{"id":"SONSEWJ12AB0182FBB","title":"Abbeville Fair"}},{"artist":{"name":"SOJA"},"song":{"id":"SOONUVQ12AB018889B","title":"Be Aware"}},{"artist":{"name":"Julie Roberts"},"song":{"id":"SORNAKH12AF72A1FDE","title":"The Chance"}},{"artist":{"name":"Koffi OlomidA(c)"},"song":{"id":"SOVPBXO12AB0188671","title":"Bennie"}},{"artist":{"name":"Herbert von Karajan and Turin RAI Symphony Orchestra"},"song":{"id":"SOCIKUA12AB0180275","title":"Symphony No. 7 in A Major_ Op. 92: I. Poco sostenuto - Vivace"}},{"artist":{"name":"Mustafa Sandal / GA1/4lcan"},"song":{"id":"SOTKIHB12A8C13F653","title":"Aya Benzer 2003 (Moonlight)"}},{"artist":{"name":"Harald Kloser / Thomas Wander / Thomas Schobel"},"song":{"id":"SORMKJM12AB017A911","title":"Opening"}},{"artist":{"name":"Bela Fleck And The Flecktones"},"song":{"id":"SOFLGMJ12AB01885F6","title":"Michelle (LP Version)"}},{"artist":{"name":"Bitty McLean"},"song":{"id":"SOJINJO12A8C13C8C9","title":"WeA\u0027ve Only Just Begun"}},{"artist":{"name":"Thrice"},"song":{"id":"SOUQYYT12A8C13BA09","title":"Betrayal Is A Symptom"}},{"artist":{"name":"MichA\"le Bernard"},"song":{"id":"SOARJWK12AC46862BB","title":"Le mouton dans la baignoire"}},{"artist":{"name":"Isabel Pantoja"},"song":{"id":"SODVZLU12A8C13FE90","title":"Como Nadie Te He Querido"}},{"artist":{"name":"The Robert Cray Band"},"song":{"id":"SOFMFBW12AB0183457","title":"Phone Booth"}},{"artist":{"name":"True Believers"},"song":{"id":"SOFQFTY12A8C1369E9","title":"Stranger"}},{"artist":{"name":"Kristine W."},"song":{"id":"SOLQRVO12AB01860FB","title":"I\u0027ll Be Your Light (Ian Nieman Remix)"}},{"artist":{"name":"Robin Beanland"},"song":{"id":"SOJPCYV12AB017C9D3","title":"Test Of The Terrarium"}},{"artist":{"name":"Guitar Slim"},"song":{"id":"SOGODAQ12A58A7AAA7","title":"Hello_ How Ya Been? Goodbye  (LP Version)"}},{"artist":{"name":"Kate Maki"},"song":{"id":"SOXCQLQ12AB017DC0B","title":"I\u0027ll Be Here in the Morning"}},{"artist":{"name":"Roberto Roena"},"song":{"id":"SORUZIY12AC4686C65","title":"Let It Rain"}},{"artist":{"name":"Geier Sturzflug"},"song":{"id":"SODHWXG12A6D4F9F87","title":"Schwarzarbeit"}},{"artist":{"name":"Beatnuts featuring Tony Touch"},"song":{"id":"SOKYKFF12A8C131FEB","title":"Cocotaso featuring Tony Touch"}},{"artist":{"name":"Belphegor"},"song":{"id":"SOTGMEB12A8C13B4CC","title":"The Sukkubus Lustrate"}},{"artist":{"name":"Jay PA(c)rez"},"song":{"id":"SOJLKSL12AB0183D93","title":"America the Beautiful"}},{"artist":{"name":"Daryl Coley"},"song":{"id":"SOLKQVW12A6D4F69AB","title":"Standing On The Promises (Palmore) (Beyond The Veil Album Version)"}},{"artist":{"name":"Benga"},"song":{"id":"SOWLAQT12A8C13D037","title":"Zero M2"}},{"artist":{"name":"Obie Bermudez"},"song":{"id":"SOYRKAG12A8C13D7A0","title":"Celos"}},{"artist":{"name":"Kiprich"},"song":{"id":"SOJJATE12A8AE46A59","title":"Dash Way Belly"}},{"artist":{"name":"Beenie Man"},"song":{"id":"SOFTBKK12AB018816C","title":"Million Gal"}},{"artist":{"name":"Bukka White"},"song":{"id":"SOCUPHK12A6D4FC491","title":"Aberdeen Blues"}},{"artist":{"name":"Barbara Fairchild"},"song":{"id":"SOQMCZO12A58A7ADAD","title":"Jezebel"}},{"artist":{"name":"The Panic Channel"},"song":{"id":"SOCCMWP12A58A7919C","title":"Said You\u0027d Be"}},{"artist":{"name":"Jimmy Page_ John Paul Jones_ Albert Lee_ Nicky Hopkins_ Big Jim Sullivan_ Clem Cattini_ Chris Hughes"},"song":{"id":"SOYUULR12AF72AB86D","title":"Livin\u0027 Lovin\u0027 Wreck"}},{"artist":{"name":"Elton Britt"},"song":{"id":"SOJSKZX12A58A7DE0E","title":"Little Silver Bells"}},{"artist":{"name":"Between The Buried And Me"},"song":{"id":"SOFRITM12A81C20954","title":"Prequel To The Sequel (Album Version)"}},{"artist":{"name":"Reginaldo Bessa"},"song":{"id":"SOYZHDL12AB01864AF","title":"Gosto de VocAa Demais"}},{"artist":{"name":"Cybertribe"},"song":{"id":"SOOMYIJ12A8C133601","title":"Cry Of The Earth"}},{"artist":{"name":"Beenie Man"},"song":{"id":"SOHGXBL12AB0183D01","title":"Stack and Pile"}},{"artist":{"name":"Laurie Berkner"},"song":{"id":"SOKJDLN12AB01826D9","title":"Ice Cream Cone"}},{"artist":{"name":"Marilyn Horne"},"song":{"id":"SONGUIH12A6D4F9274","title":"Agrippina : Act 3 \"Bel piacere A\" godere fido amor!\" [Poppea]"}},{"artist":{"name":"RyanDan"},"song":{"id":"SOVCDEV12A6D4FCD04","title":"Wind Beneath My Wings"}},{"artist":{"name":"Herbert  von Karajan"},"song":{"id":"SOJBWKS12A8C135255","title":"Oedipus Rex_ Atto Primo: Liberi_ Vos Liberabo (Oedipus) (Stravinsky)"}},{"artist":{"name":"Albert Ayler"},"song":{"id":"SOEWUBS12A6D4F8DB0","title":"Ghosts_ Second Variation"}},{"artist":{"name":"Johnny Otis Show"},"song":{"id":"SOBWEEH12A58A7D3EC","title":"You Better Look Out"}},{"artist":{"name":"Sammi Cheng"},"song":{"id":"SOBRVUL12A6D4F9903","title":"Nu Ren Ben Se"}},{"artist":{"name":"Obie Bermudez"},"song":{"id":"SOHHASC12A8C139D11","title":"Antes (Salsa Version)"}},{"artist":{"name":"Ben Sidran"},"song":{"id":"SOMASOQ12AB018ACC8","title":"Everybody\u0027s boppin\u0027"}},{"artist":{"name":"Ice Cube Featuring Flavor Flav"},"song":{"id":"SOGFLWF12A6D4F64AC","title":"I\u0027m Only Out For One Thang (Explicit) (Feat. Flavor Flav)"}},{"artist":{"name":"VHS Or Beta"},"song":{"id":"SOCNTQV12A6D4F4ADD","title":"You Got Me (The Juan Maclean Dub)"}},{"artist":{"name":"Babe Ruth"},"song":{"id":"SODHRKU12A8C139009","title":"A Fistful Of Dollars (1994 Digital Remaster)"}},{"artist":{"name":"Amy Winehouse"},"song":{"id":"SOVKRNJ12CF5F876BB","title":"In My Bed"}},{"artist":{"name":"Steve Chou"},"song":{"id":"SONLMRH12AAF3B282D","title":"Pi Jiu Pao Pao (Beer Bubbles)"}},{"artist":{"name":"Between The Buried And Me"},"song":{"id":"SOMPGSD12A58A7F840","title":"Kickstart My Heart (Album Version)"}},{"artist":{"name":"The Motors"},"song":{"id":"SOVHCNH12AB0180DD6","title":"You Beat The Hell Outta Me"}},{"artist":{"name":"Alan Feinberg"},"song":{"id":"SOZMHGF12AB017E01C","title":"Menuet in the Name of Haydn"}},{"artist":{"name":"Karen Peck \u0026 New River"},"song":{"id":"SOMTOKI12A8C13AE40","title":"Behind The Line Of Grace"}},{"artist":{"name":"Roberto Perera"},"song":{"id":"SOCWFBD12AB018BB72","title":"A Puro Dolor"}},{"artist":{"name":"Beenie Man"},"song":{"id":"SOJGADT12A81C22EAB","title":"Politrix"}},{"artist":{"name":"Greater Vision"},"song":{"id":"SOBJZRJ12A8C13EB0C","title":"Carol Of The Bells (Instramental Featuring The Budapest Pops Orchestra)"}},{"artist":{"name":"Danny Wright"},"song":{"id":"SOEFJXQ12A670200C8","title":"Carol of the Bells (Album Version)"}},{"artist":{"name":"The Chico Hamilton Quintet With Fred Katz_ Paul Horn_ John Pisano_ Carson Smith"},"song":{"id":"SOTAEHU12A8AE47888","title":"September Song"}},{"artist":{"name":"Sue Foley"},"song":{"id":"SOBRDLW12AC468A908","title":"She Don\u0027t Belong To You"}},{"artist":{"name":"Ben Sidran"},"song":{"id":"SOCJHAZ12AB0181CE2","title":"Blowin\u0027 In the Wind"}},{"artist":{"name":"Joy Division"},"song":{"id":"SOEEANS12AB0184A71","title":"The Sound Of Music - [High Wycombe Town Hall Live 13 July 1979] (Sound Check)"}},{"artist":{"name":"Mariano Yanani"},"song":{"id":"SOEHDVV12A8C140A53","title":"Canon In D Major (J. Pachelbel)"}},{"artist":{"name":"Aphasia"},"song":{"id":"SOWZQFZ12AB018AC54","title":"non-existent track (part one: \"why don\u0027t you fuckin\u0027 remember anything ?\")"}},{"artist":{"name":"Beherit"},"song":{"id":"SOYYJNB12AB0184408","title":"Suck My Blood"}},{"artist":{"name":"Elvin Bishop"},"song":{"id":"SOOBTKZ12A58A7B0B0","title":"I\u0027ll Be Glad"}},{"artist":{"name":"Beautiful Creatures"},"song":{"id":"SOYULPJ12A67021002","title":"Wish (Album Version)"}},{"artist":{"name":"Nightwish"},"song":{"id":"SOLDLXG12AB0185707","title":"Beauty And The Beast"}},{"artist":{"name":"Rod Bernard"},"song":{"id":"SOAVTUX12AB0181896","title":"Cajun Honey (Cajun Lovin\u0027 Style)"}},{"artist":{"name":"Gorillaz"},"song":{"id":"SOLJQBW12A6702187B","title":"November Has Come"}},{"artist":{"name":"The John Buzon Trio"},"song":{"id":"SOBUDGS12AB0184923","title":"I Can\u0027t Believe That You\u0027re In Love With Me (Digitally Remastered 95)"}},{"artist":{"name":"Robert Lockwood_ Jr."},"song":{"id":"SOLKVUE12AB018352E","title":"Big Legged Woman"}},{"artist":{"name":"Peloton"},"song":{"id":"SOUAFUV12AB018A8FC","title":"Beloki"}},{"artist":{"name":"Eddie"},"song":{"id":"SOWKNZT12AC4688FC9","title":"Beautiful Lies"}},{"artist":{"name":"Telecast"},"song":{"id":"SOFCFGG12A6D4FB5F8","title":"Covered (The Beauty Of Simplicity Album Version)"}},{"artist":{"name":"God Lives Underwater"},"song":{"id":"SOPWHEV12AB017DC10","title":"Don\u0027t Know How To Be"}},{"artist":{"name":"Fake Problems"},"song":{"id":"SOYKZHI12A58A7BEE9","title":"Tabernacle Song"}},{"artist":{"name":"ATB"},"song":{"id":"SOWPSXC12A6D4FB04D","title":"Collides With Beauty"}},{"artist":{"name":"Jeanie Lambe \u0026 The Danny Moss Quartet"},"song":{"id":"SOFLQOA12AB0182976","title":"My Funny Valentine"}},{"artist":{"name":"BerrogA1/4etto"},"song":{"id":"SOGMYFZ12AC468ACED","title":"Nadal De Luintra"}},{"artist":{"name":"Michael Jackson"},"song":{"id":"SOQUAIH12AB0181406","title":"I Wanna Be Where You Are"}},{"artist":{"name":"The Shangri-Las"},"song":{"id":"SOBDYCT12AB0183AF5","title":"Remember (Walkin\u0027 In the Sand)"}},{"artist":{"name":"Abbott \u0026 Chambers"},"song":{"id":"SOOUEFP12A81C2272E","title":"Never After"}},{"artist":{"name":"Karen Peck And New River"},"song":{"id":"SOOCIQX12A6D4F92D3","title":"My God Will Always Be Enough"}},{"artist":{"name":"A Tribe Called Quest"},"song":{"id":"SOFCKEK12A8AE46966","title":"Like It Like That"}},{"artist":{"name":"VHS Or Beta"},"song":{"id":"SOIIZQG12A58A7A753","title":"New Day Rising"}},{"artist":{"name":"Alice Cooper"},"song":{"id":"SOTJZBJ12A8C143A71","title":"Be My Lover"}},{"artist":{"name":"Dobet GnahorA(c)"},"song":{"id":"SOYWXIK12AB017C22B","title":"Kakou"}},{"artist":{"name":"John Berry"},"song":{"id":"SONOVXO12AB01877FE","title":"Those Were the Days"}},{"artist":{"name":"Gene Chandler"},"song":{"id":"SOMYYQD12AB0184CE2","title":"I Hate to Be the One to Say"}},{"artist":{"name":"Cecilia Bartoli / International Chamber Soloists / Orchestra La Scintilla / Adam Fischer"},"song":{"id":"SOFJCSH12A81C20934","title":"Se un mio desir...Cedi al duo!"}},{"artist":{"name":"Anthony Watson"},"song":{"id":"SOFFIQX12AC960DA6E","title":"I Love Being Single (club extended mix)"}},{"artist":{"name":"Benny Spellman"},"song":{"id":"SOEBVZQ12AB01869D3","title":"I Didn\u0027t Know"}},{"artist":{"name":"Beres Hammond Feat. Jah Youth"},"song":{"id":"SOAKCBR12A6D4F6D04","title":"Good Old Dancehall Vibes"}},{"artist":{"name":"Terry Dexter"},"song":{"id":"SODHUER12AB018859B","title":"Beautiful One"}},{"artist":{"name":"Bebo Norman"},"song":{"id":"SOAVNNL12A8C145B33","title":"Britney"}},{"artist":{"name":"Alan Silvestri"},"song":{"id":"SOENCQG12A8C13599B","title":"Not Meant To Be Found"}},{"artist":{"name":"George Faith"},"song":{"id":"SOTQOSY12A67021C2D","title":"If Loving You Is Wrong I Don\u0027t Wanna Be Right"}},{"artist":{"name":"The Tall Grass"},"song":{"id":"SODDUKA12AB0187DF4","title":"Be \u0026 Flower"}},{"artist":{"name":"Kenny G"},"song":{"id":"SOSYKKS12A8C1388DF","title":"I\u0027ve Been Missin\u0027 You"}},{"artist":{"name":"impulsonic"},"song":{"id":"SOKNQNE12A8C146767","title":"Beats are my Weapons"}},{"artist":{"name":"SWAMI featuring Ishmael Morabe"},"song":{"id":"SONUHEM12AB01899D0","title":"Break"}},{"artist":{"name":"Big Maybelle"},"song":{"id":"SOZCOAI12A8C1332A9","title":"Tell Me Who"}},{"artist":{"name":"Belle \u0026 Sebastian"},"song":{"id":"SOFCFSC12B0B80ACDB","title":"Stay Loose"}},{"artist":{"name":"Berlin"},"song":{"id":"SOAEGMV12A8C1455F2","title":"Blink Of An Eye (Alternative)"}},{"artist":{"name":"BeyoncA(c)"},"song":{"id":"SOMBVNV12A8C1361F0","title":"Krazy In Luv"}},{"artist":{"name":"Fiona"},"song":{"id":"SOITKGP12A58A75D98","title":"Since I\u0027ve Been Loving You"}},{"artist":{"name":"Cali"},"song":{"id":"SOIABUP12AAF3B55F2","title":"Betty Et Tommy (Instrumental)"}},{"artist":{"name":"Justin Timberlake"},"song":{"id":"SOTSCLM12AF72A097D","title":"Sexy Ladies"}},{"artist":{"name":"Luke Vibert"},"song":{"id":"SORIGHO12AB0184BED","title":"LFO [Original by LFO]"}},{"artist":{"name":"Bruce BecVar"},"song":{"id":"SOIKAUS12AB018AD93","title":"Your Heart Can Sing"}},{"artist":{"name":"Robert Lockwood_ Jr."},"song":{"id":"SOJTITX12AB0183525","title":"Feel Like Blowing My Horn"}},{"artist":{"name":"Bescenta"},"song":{"id":"SOKAAAY12AB0186459","title":"Why"}},{"artist":{"name":"Bert Kaempfert And His Orchestra"},"song":{"id":"SOFKVJV12A6D4F8F4B","title":"Talk"}},{"artist":{"name":"The Exciters"},"song":{"id":"SOPOWJI12A8C14159F","title":"Reaching For The Best"}},{"artist":{"name":"Natasha Bedingfield"},"song":{"id":"SORTSWB12A58A7DCA3","title":"These Words"}},{"artist":{"name":"Regina Belle"},"song":{"id":"SOJRXHM12A8C13D93E","title":"Quiet Time"}},{"artist":{"name":"Tam Tam Go!"},"song":{"id":"SOKSRRN12A8C135415","title":"Better Ways"}},{"artist":{"name":"Maddox Brothers and Rose"},"song":{"id":"SOKHGCN12A8C13CFFE","title":"Jingle Bells"}},{"artist":{"name":"Alternative TV"},"song":{"id":"SOLFOLX12A8C1443AB","title":"Dub In Bed"}},{"artist":{"name":"ATB"},"song":{"id":"SOHBOGO12A8C13B8F8","title":"Believe In Me (Clubb Mix)"}},{"artist":{"name":"Marco Beltrami"},"song":{"id":"SOVDSBD12A8C13DF47","title":"Dead Hackers"}},{"artist":{"name":"Berlin"},"song":{"id":"SOLQWHJ12A8C135A13","title":"Now It\u0027s My Turn (Aqualite Mix)"}},{"artist":{"name":"Aphasia"},"song":{"id":"SOTOVKU12AB018AC33","title":"sample processing failed (part one: \"why don\u0027t you fuckin\u0027 remember anything ?\")"}},{"artist":{"name":"Blue October"},"song":{"id":"SOECRTE12A8C14296D","title":"Blue Skies"}},{"artist":{"name":"Joa~o Gilberto"},"song":{"id":"SOVAGPG12AB0189963","title":"Samba De Una Nota SoA\u0027"}},{"artist":{"name":"Uriah Heep"},"song":{"id":"SONXFRI12AB018726F","title":"What Should Be Done"}},{"artist":{"name":"Martina McBride"},"song":{"id":"SODNCTF12AB0187B92","title":"Make Me Believe"}},{"artist":{"name":"Becoming The Archetype"},"song":{"id":"SOEGWFT12A6D4F89FD","title":"Ex Nihilo"}},{"artist":{"name":"Bebo Norman"},"song":{"id":"SOSUCQN12A8C141DFF","title":"Sunday"}},{"artist":{"name":"Aeoliah"},"song":{"id":"SOLZHTJ12A8C1370B8","title":"Temple Bells"}},{"artist":{"name":"Inner Circle"},"song":{"id":"SOPMWKF12AC961828D","title":"Bed\u0027s Too Big Without You"}},{"artist":{"name":"Ray Conniff"},"song":{"id":"SOLBBCS12AC468D6D0","title":"Something To Remember You By"}},{"artist":{"name":"The Robert Cray Band"},"song":{"id":"SOODHEW12A6D4F8E96","title":"Far Away (Album Version)"}},{"artist":{"name":"Toby Love Feat. Girlz Talk"},"song":{"id":"SOYWTMP12AB017B32B","title":"Yo Quiero Saber"}},{"artist":{"name":"Corona"},"song":{"id":"SOIXFAQ12A8C13F588","title":"You Gotta Be Movin\u0027"}},{"artist":{"name":"John Berry"},"song":{"id":"SOKSBBB12A6D4F653A","title":"Ninety Miles An Hour"}},{"artist":{"name":"Aisha Duo"},"song":{"id":"SOUGLCH12A8C140306","title":"Beneath an Evening Sky"}},{"artist":{"name":"Marco Beltrami"},"song":{"id":"SOPUGFD12A6D4FB501","title":"Nomads Alive"}},{"artist":{"name":"Laurie Berkner"},"song":{"id":"SOMRQXT12AB017F9E9","title":"Zodiac"}},{"artist":{"name":"Slackbaba"},"song":{"id":"SOKCQWQ12AB0189111","title":"And The Beat Goes Om"}},{"artist":{"name":"Ebba Forsberg"},"song":{"id":"SOJWIRI12AB01841A7","title":"Halleluja"}},{"artist":{"name":"Montserrat CaballA(c)/Royal Philharmonic Orchestra/Lamberto Gardelli"},"song":{"id":"SOGNZTE12A67AD8518","title":"Guillaume Tell_ Acte II (1988 Digital Remaster): Ils s\u0027A(c)loignent enfin....Sombre forAat"}},{"artist":{"name":"Tam Tam Go!"},"song":{"id":"SOTUHTD12A8C133D88","title":"Belleza Pasajera"}},{"artist":{"name":"3 Doors Down"},"song":{"id":"SOVJHFQ12A8C13BBF1","title":"Be Like That"}},{"artist":{"name":"Christophe Beck"},"song":{"id":"SOFLXUY12A8C1364F6","title":"Why Jack Called"}},{"artist":{"name":"L.a. Dream Team"},"song":{"id":"SODVBYU12A8C13CB5B","title":"Rockberry Jam"}},{"artist":{"name":"Marco Beltrami"},"song":{"id":"SONEXQJ12AAF3B2A3D","title":"Not A Kid Anymore"}},{"artist":{"name":"Seventh Day Slumber"},"song":{"id":"SOXJXPH12A58A7E199","title":"Sabados"}},{"artist":{"name":"The Villas"},"song":{"id":"SOKJEMV12A8C1374AD","title":"To Be In Love"}},{"artist":{"name":"Will Ackerman"},"song":{"id":"SOCFGRK12A8C137C8C","title":"A Movie Of A Placid Lake On A Moonless Night In September - Reprise"}},{"artist":{"name":"The Berzerker"},"song":{"id":"SORGPNH12AF72AB8C0","title":"Pure Hatred"}},{"artist":{"name":"Ambient Music Therapy"},"song":{"id":"SOBNNRV12AB0186ED3","title":"Voice of Angels Drone for Spiritual Well Being"}},{"artist":{"name":"Jessica Simpson"},"song":{"id":"SODANQM12CF5F890BC","title":"Be"}},{"artist":{"name":"Kaija Koo"},"song":{"id":"SONIYKB12A8C13C92A","title":"Tule lA$?hemmA$?s Beibi"}},{"artist":{"name":"Jimmy Page / Robert Plant"},"song":{"id":"SOZKYCJ12A6D4F480A","title":"Thank You"}},{"artist":{"name":"Beastie Boys"},"song":{"id":"SOHLMRI12AB0180B3D","title":"Flute Loop (2009 Digital Remaster)"}},{"artist":{"name":"Penguin CafA(c) Orchestra"},"song":{"id":"SOWZMBC12A6D4FB3BB","title":"Bean Fields (Live) (2001 Digital Remaster)"}},{"artist":{"name":"Leroy Hutson"},"song":{"id":"SOTBFHX12AB0183936","title":"All Because Of You - Original"}},{"artist":{"name":"Derek Bell"},"song":{"id":"SOQDIQK12A8C13CB23","title":"Sake In The Jar"}},{"artist":{"name":"Margaret Becker"},"song":{"id":"SOWJFHF12AF72A7603","title":"Just Come In"}},{"artist":{"name":"Be Bop Deluxe"},"song":{"id":"SODJFJT12A6D4F67EB","title":"Piece Of Mine"}},{"artist":{"name":"NOFX"},"song":{"id":"SOOFUMT12A8C133296","title":"We March To The Beat Of Indifferent Drum"}},{"artist":{"name":"Jeff Beck"},"song":{"id":"SOOSHFN12A8C14371B","title":"Angel [Footsteps] (Album Version)"}},{"artist":{"name":"MetsatAPll"},"song":{"id":"SOZOSQN12AB01872A1","title":"Kui rebeneb taevas"}},{"artist":{"name":"Charlie Louvin"},"song":{"id":"SOQSEBZ12AB017E984","title":"Just Between The Two Of Us"}},{"artist":{"name":"John Pagano_ Burt Bacharach"},"song":{"id":"SOAOFMX12A8C1421AD","title":"I Still Remember"}},{"artist":{"name":"Pery Ribeiro"},"song":{"id":"SODBYFM12A8C13F6BA","title":"Momento De Amor"}},{"artist":{"name":"The Chinese"},"song":{"id":"SOZWKVV12A58A7AB8D","title":"I\u0027ll Be There For You (Alternate Mix)"}},{"artist":{"name":"Albert King"},"song":{"id":"SONLCCI12A8C140225","title":"Please Come Back To Me - Live"}},{"artist":{"name":"Luis Alberto Spinetta"},"song":{"id":"SOCNERX12A8C13B845","title":"Oh! Doctor"}},{"artist":{"name":"Kyle Riabko"},"song":{"id":"SOUYAQM12A8C13802C","title":"Doesn\u0027t Get Much Better"}},{"artist":{"name":"Eliane Elias"},"song":{"id":"SOOIWMK12A6D4F6972","title":"The Beat Of My Heart"}},{"artist":{"name":"Janis Joplin"},"song":{"id":"SOZTFAZ12A8AE46630","title":"Maybe"}},{"artist":{"name":"Fontaine Sisters"},"song":{"id":"SOFYNGP12A8C13AB56","title":"Silver Bells"}},{"artist":{"name":"Ruben Cossani"},"song":{"id":"SOVHCTD12AC9E154F7","title":"Piroschka"}},{"artist":{"name":"Beres Hammond Feat. Natural Black"},"song":{"id":"SOPNFOE12A8AE48AC9","title":"Let The Good Times Roll"}},{"artist":{"name":"Leon Berry"},"song":{"id":"SOCJBTQ12A6D4FA539","title":"Waltzing Matilda"}},{"artist":{"name":"N.W.A."},"song":{"id":"SOWIGGR12A6D4F6CC4","title":"Bonus Beats (2002 Digital Remaster)"}},{"artist":{"name":"BeyoncA(c) feat. Slim Thug"},"song":{"id":"SOKXYUW12A8C140229","title":"Check On It"}},{"artist":{"name":"Maria \u0026 Margot Hellwig/Thomas Lehrberger"},"song":{"id":"SOEOVBX12AB0189E1C","title":"La Montanara"}},{"artist":{"name":"Prince \u0026 Tevin Campbell"},"song":{"id":"SONSHOY12A8C13E81D","title":"Round and Round ( LP Version )"}},{"artist":{"name":"Gloriana"},"song":{"id":"SOWXUHS12AB01888EE","title":"Bambenella d\u0027 \u0027o mercato"}},{"artist":{"name":"Bersuit Vergarabat"},"song":{"id":"SOBVPQV12AB018353C","title":"Se Viene"}},{"artist":{"name":"Ann Hampton Callaway;Laura Benanti;Michael Gruber;Everett Bradley"},"song":{"id":"SOAPYOS12A8C133890","title":"Stompin\u0027 at the Savoy"}},{"artist":{"name":"Beres Hammond"},"song":{"id":"SODBQYW12A6D4F6CFA","title":"Call On The Father"}},{"artist":{"name":"Tullycraft"},"song":{"id":"SOFMZFX12AB018437A","title":"Bee Sting Stings"}},{"artist":{"name":"Panzer AG"},"song":{"id":"SOEROGE12A6D4FACDD","title":"bereit"}},{"artist":{"name":"Mariano Yanani"},"song":{"id":"SOZVKHH12A8AE471B6","title":"Could You Be Love"}},{"artist":{"name":"Ray Barretto"},"song":{"id":"SOYRWCZ12A58A7F91B","title":"Guarare (Live At The Beacon Theatre)"}},{"artist":{"name":"K-OS"},"song":{"id":"SORVKAX12A8C1343AA","title":"Man I Used To Be"}},{"artist":{"name":"MIMS Featuring J. Holiday"},"song":{"id":"SOHVIKX12A58A7D0ED","title":"Be My Hustla (Explicit) (Feat. J. Holiday)"}},{"artist":{"name":"Los Fabulosos Cadillacs"},"song":{"id":"SOIGZOE12AB017F37D","title":"Vos Sabes"}},{"artist":{"name":"Albert PrA(c)jean"},"song":{"id":"SOXWHXX12AB018E307","title":"Une java"}},{"artist":{"name":"Glad"},"song":{"id":"SODOOMF12AB018D375","title":"This is My Father\u0027s World/For the Beauty of the Earth"}},{"artist":{"name":"Glen Campbell"},"song":{"id":"SOWWTHH12A81C237FE","title":"After The Glitter Fades (LP Version)"}},{"artist":{"name":"Herbert Von Karajan"},"song":{"id":"SORJXMA12A8C13924B","title":"Conc Orchestre Sz.116/Allegretto (2eme Mvt)"}},{"artist":{"name":"Sandy Lam"},"song":{"id":"SOJOICW12A8C13B533","title":"Shi Guang Ben Shi Wu Zui"}},{"artist":{"name":"Ebba Forsberg"},"song":{"id":"SODCSUB12AC90716E6","title":"Ta Min Vals (Take This Waltz)"}},{"artist":{"name":"Moist"},"song":{"id":"SOTJTQO12AB0183126","title":"Far Beyond The Endless"}},{"artist":{"name":"Dons"},"song":{"id":"SOENANC12A8C134906","title":"Best Kept Secret"}},{"artist":{"name":"Beenie Man"},"song":{"id":"SOORYUV12AB0183C3E","title":"Cross The Bridge"}},{"artist":{"name":"Hanoi Rocks"},"song":{"id":"SONAMOI12AB0182AA1","title":"Mental Beat"}},{"artist":{"name":"Jessica Myrberg"},"song":{"id":"SOKECHN12AB0185200","title":"I Love Rock nA\u0027 Roll"}},{"artist":{"name":"Seventh Day Slumber"},"song":{"id":"SOYCYPP12AB0185E21","title":"Lead Me To The Cross (Acoustic)"}},{"artist":{"name":"Andy \u0026 Lucas"},"song":{"id":"SOLVMKY12A8C13A5AE","title":"Dame Un Besito (Version Salsa)"}},{"artist":{"name":"Marco Beltrami"},"song":{"id":"SORSTYX12A6D4FB4FB","title":"Franks Plea"}},{"artist":{"name":"Oscar Lima"},"song":{"id":"SOQELHR12AC4689565","title":"If You Wanna Be My Friend"}},{"artist":{"name":"Trafik"},"song":{"id":"SOPFOCW12A8C134550","title":"Le Beeatch"}},{"artist":{"name":"Thomas Battenstein"},"song":{"id":"SOIDDGN12AB018371D","title":"Plage de Belle Maison"}},{"artist":{"name":"David Robertson"},"song":{"id":"SOXNVDF12A8C1343BA","title":"Love Is An Uphill Climb  ()"}},{"artist":{"name":"Smokin\u0027 Joe Kubek \u0026 Bnois King"},"song":{"id":"SOETKNB12A6D4FCC6A","title":"Tell Me Why"}},{"artist":{"name":"Mario Rosenstock"},"song":{"id":"SONZCGY12A8C1403C1","title":"Mercedes Benz"}},{"artist":{"name":"DJ Deeon"},"song":{"id":"SOKDCSL12A8C13B736","title":"Rubber Track"}},{"artist":{"name":"Apache Indian"},"song":{"id":"SOGNPYN12A6D4F9078","title":"Real People (Cybernetic Dub)"}},{"artist":{"name":"Leana"},"song":{"id":"SOSQVWS12A8C13695C","title":"Pack Your Bags (Jake Benson Club Mix)"}},{"artist":{"name":"Soulwax"},"song":{"id":"SOHYWLZ12A6D4FBB22","title":"Much Against Everyone\u0027S Advice (Dave Bascombe Radio Mix)"}},{"artist":{"name":"Dionne Warwick"},"song":{"id":"SOWWUUZ12A6D4FA8CA","title":"I\u0027ve Been Loving You Too Long (LP Version)"}},{"artist":{"name":"Pelle Carlberg"},"song":{"id":"SONQCXQ12AB017BBAE","title":"I Love You_ You Imbecile"}},{"artist":{"name":"Marco Beltrami"},"song":{"id":"SOZMZZO12AB0180F1B","title":"The Wrapper"}},{"artist":{"name":"Tracy Byrd"},"song":{"id":"SOWMQNJ12A8AE471EE","title":"Just Let Me Be In Love"}},{"artist":{"name":"Cindy Morgan"},"song":{"id":"SOOXNKG12A58A7C6BC","title":"Someone Believes In You - Album Version"}},{"artist":{"name":"Isabelle Adjani"},"song":{"id":"SOSZDPD12A6D4F6ECA","title":"Entre Autre Pas En TraA(r)tre"}},{"artist":{"name":"The Winans"},"song":{"id":"SOXIFNK12AB0186B11","title":"Don\u0027t Be Deceived"}},{"artist":{"name":"Roy Roberts"},"song":{"id":"SOIVXLP12A8C139F26","title":"Let\u0027s Wrap Up"}},{"artist":{"name":"Luis Alberto Spinetta"},"song":{"id":"SOTBODD12A8C13D628","title":"Alfil_ Ella No Cambia Nada"}},{"artist":{"name":"Lennie Tristano"},"song":{"id":"SOBXDCF12A6701FAFC","title":"Becoming (LP Version)"}},{"artist":{"name":"Fast Eddie"},"song":{"id":"SOVOFIU12AF72AD12F","title":"Put On Your Rubbers"}},{"artist":{"name":"Eagles Of Death Metal"},"song":{"id":"SOLADTL12AB01815A7","title":"As Nice As I Can Be"}},{"artist":{"name":"Beatnuts with Lil\u0027 Donny"},"song":{"id":"SOUCZVQ12A8C131FF0","title":"Spelling Beatnuts with Lil\u0027 Donny"}},{"artist":{"name":"Colin James"},"song":{"id":"SOTUGEK12AB018BE28","title":"Better Days"}},{"artist":{"name":"Shadows Fall"},"song":{"id":"SOSZSGF12A67AE21B1","title":"Crushing Belial"}},{"artist":{"name":"John Davis"},"song":{"id":"SOXMSDY12A8C142C7E","title":"Silver Bells"}},{"artist":{"name":"Barry Goldberg"},"song":{"id":"SOUTQDI12A67AE11FD","title":"Lost Love"}},{"artist":{"name":"The Summer Obsession"},"song":{"id":"SOBWXDJ12A58A7725D","title":"Where You Belong"}},{"artist":{"name":"Beth Nielsen Chapman"},"song":{"id":"SOQBXKB12AB018A727","title":"Fair Enough (LP Version)"}},{"artist":{"name":"Go Fish"},"song":{"id":"SOAXVMJ12A8C1352E7","title":"I Believe In You (More Than A Story Album Version)"}},{"artist":{"name":"Maroon 5"},"song":{"id":"SOKYZSI12AB0183789","title":"She Will Be Loved"}},{"artist":{"name":"Corona"},"song":{"id":"SOBFBEK12AB017FC1B","title":"I Don\u0027t Wanna be A Star"}},{"artist":{"name":"Jody Bernal"},"song":{"id":"SOQLEJT12A6D4F8BFE","title":"Que Si_ Que No"}},{"artist":{"name":"Beherit"},"song":{"id":"SOOKXRZ12AB01821D4","title":"Sense"}},{"artist":{"name":"Justin Timberlake"},"song":{"id":"SOOHWCX12A8AE48B59","title":"Love Don\u0027t Love Me (Justin Timberlake) (Amended Version)"}},{"artist":{"name":"Sharon Burch"},"song":{"id":"SOFJQTP12AAFF4441E","title":"Don\u0027t Be Afraid (World)"}},{"artist":{"name":"David Jalbert"},"song":{"id":"SONALZR12AC4688B15","title":"North American Ballads: No. 2 - Which Side Are You On?"}},{"artist":{"name":"Cassidy featuring Swizz Beatz"},"song":{"id":"SOFEISR12A8C1421FB","title":"I Get My Paper"}},{"artist":{"name":"Joy Enriquez"},"song":{"id":"SOJDKVC12A8C13927A","title":"Between You And Me"}},{"artist":{"name":"Groupa"},"song":{"id":"SOROXBU12A8C13F3D6","title":"Bliv Du Till Gran (If You Became A Spruce)"}},{"artist":{"name":"Josh White"},"song":{"id":"SOISQVL12AB0181716","title":"Jesus Is Gonna Make Up My Dying Bed"}},{"artist":{"name":"Gaither Vocal Band"},"song":{"id":"SOEYHXW12A8C13C677","title":"Knowing You\u0027ll Be There"}},{"artist":{"name":"Bill Cosby"},"song":{"id":"SOSVNTG12A6D4FA27F","title":"Fat Albert\u0027s Car"}},{"artist":{"name":"Tony Joe White"},"song":{"id":"SOCFLRO12A6D4FA981","title":"Yo Yo Man (Garter Belt)"}},{"artist":{"name":"Telecast"},"song":{"id":"SOZQTSL12A6D4FB5F6","title":"Remember (The Beauty Of Simplicity Album Version)"}},{"artist":{"name":"Dionne Warwick"},"song":{"id":"SOVHKAC12AB018C763","title":"Let It Be Me"}},{"artist":{"name":"Belphegor"},"song":{"id":"SOYFVFU12A8C13B4BE","title":"Armageddon\u0027s Raid"}},{"artist":{"name":"STEVE CAMP"},"song":{"id":"SORYAVK12A8C13A10E","title":"Judgement Begins With The House Of God"}},{"artist":{"name":"Cornel Campbell"},"song":{"id":"SOSJYYD12A8AE480DC","title":"Somebody Has Stolen My Girl"}},{"artist":{"name":"Bert Kaempfert"},"song":{"id":"SOCUSAL12AB0182310","title":"Sugar Bush"}},{"artist":{"name":"Pery Ribeiro"},"song":{"id":"SOQXARY12A8C13F68C","title":"Piano E Viola"}},{"artist":{"name":"Christophe Beck"},"song":{"id":"SOKEGNC12A6D4FB54C","title":"Main Title"}},{"artist":{"name":"The Chieftains"},"song":{"id":"SOVXQXN12A8C135FDC","title":"No. 6 The Coombe"}},{"artist":{"name":"Hysterie"},"song":{"id":"SOQMALF12AAF3B4144","title":"Be my Lover"}},{"artist":{"name":"BerrogA1/4etto"},"song":{"id":"SOCPUJD12AC468AD40","title":"Lusco"}},{"artist":{"name":"MichA\"le Bernard"},"song":{"id":"SOAQTZJ12A8C14343C","title":"Canal de jonage"}},{"artist":{"name":"Faron Young"},"song":{"id":"SOJEECD12AB018BDA5","title":"I\u0027ll Be Yours"}},{"artist":{"name":"Mary Black \u0026 General Humbert"},"song":{"id":"SOLJMGD12A58A76C3A","title":"Isle of St. Helena"}},{"artist":{"name":"Maria Callas/Eugenio Fernandi/Elisabeth Schwarzkopf/Giuseppe Nessi/Nicola Zaccaria/Mario Borriello/Renato Ercolani/Piero de Palma/Giulio Mauri/Elisabetta Fusco/Pinuccia Perotti/Coro del Teatro alla Scala_ Milano/Orchestra del Teatro alla Scala_ Milano/Tul"},"song":{"id":"SOAQMCT12A8C1350DE","title":"Turandot (2008 Digital Remaster)_ Act III - Scene I: Nessum dorma!"}},{"artist":{"name":"Captain Beefheart \u0026 The Magic Band"},"song":{"id":"SOLEPCJ12A6D4F7404","title":"On Tomorrow"}},{"artist":{"name":"Mike And The Mechanics"},"song":{"id":"SOSAOWI12A6D4F7119","title":"Seeing Is Believing"}},{"artist":{"name":"Betika_ Daouda"},"song":{"id":"SOBBWJS12AB0182522","title":"C\u0027est pas ma faute"}},{"artist":{"name":"John Holt"},"song":{"id":"SOWYWXM12AB018C9E9","title":"Only Just Begun"}},{"artist":{"name":"Robben Ford"},"song":{"id":"SOCKRKE12AB018DD02","title":"Talk To Your Daughter (Album Version)"}},{"artist":{"name":"Curtis Mayfield"},"song":{"id":"SOSTESB12A6D4F9A66","title":"You Better Stop"}},{"artist":{"name":"The Ronettes"},"song":{"id":"SOSAQJU12AC90755D2","title":"Born To Be Together"}},{"artist":{"name":"Usher Featuring The Nu Beginning"},"song":{"id":"SOSIANM12AB018CC80","title":"Only Human"}},{"artist":{"name":"Maria Callas/Gianni Raimondi/Gabriella Carturan/Plinio Clabassi/Nicola Rossi-Lemeni/Coro del Teatro alla Scala_ Milano/Noberto Mola/Orchestra del Teatro alla Scala_ Milano/Gianandrea Gavazzeni"},"song":{"id":"SOAMZKG12A8C13797C","title":"Anna Bolena (1997 Digital Remaster): Alcun potria ascoltarti"}},{"artist":{"name":"The Shirrows"},"song":{"id":"SOGHKOU12AB018C776","title":"Leave Me Be"}},{"artist":{"name":"Dream Warriors"},"song":{"id":"SOAEGFO12A6D4F87AA","title":"Sound Clash (featuring Beenie Man) - FattaSly Extended Mix"}},{"artist":{"name":"Cornell Campbell"},"song":{"id":"SOLFRCH12A67021C28","title":"Got To Tell The People"}},{"artist":{"name":"Behemoth"},"song":{"id":"SOKZCJC12AF72A8C79","title":"Here And Beyond"}},{"artist":{"name":"Faith Hill"},"song":{"id":"SOQAUIF12AC46861CF","title":"Better Days (Album Version)"}},{"artist":{"name":"Madonna"},"song":{"id":"SOULPEW12A8C13E4F7","title":"4 Minutes [Featuring Justin Timberlake And Timbaland] [Junkie XL Remix Edit]"}},{"artist":{"name":"Behemoth"},"song":{"id":"SOYSZGR12A8C14015C","title":"Cursed Angel Of Doom (Previously Unreleased\u0026Re-Recorded Track)"}},{"artist":{"name":"Benga"},"song":{"id":"SOAPDWC12AC468BB3B","title":"The Future"}},{"artist":{"name":"Martina McBride"},"song":{"id":"SOVPTBI12AB01879CF","title":"Anything\u0027s Better Than Feelin\u0027 The Blues"}},{"artist":{"name":"U2"},"song":{"id":"SOIFMVY12A8AE467B1","title":"October"}},{"artist":{"name":"April Wine"},"song":{"id":"SOPKWZP12A6D4F7DAF","title":"Babes In Arms"}},{"artist":{"name":"Lacy J. Dalton"},"song":{"id":"SOCHJTF12AB01829CE","title":"Silver Bells"}},{"artist":{"name":"Jim Reeves"},"song":{"id":"SOWVTAJ12A8C13C6D5","title":"Jingle Bells"}},{"artist":{"name":"John Digweed"},"song":{"id":"SOUEDBC12AC90972E5","title":"Warung Beach"}},{"artist":{"name":"Death Cab for Cutie"},"song":{"id":"SONNYOP12A8AE45715","title":"You Can Do Better Than Me (Album Version)"}},{"artist":{"name":"Roberto Torres"},"song":{"id":"SOPBAMQ12A8C13A815","title":"Decima Del Tiempo De Antes"}},{"artist":{"name":"X-Raided featuring Teddy Bear_ Big Pook_ T-Nutty"},"song":{"id":"SOFAICL12AB018F914","title":"Thug Love"}},{"artist":{"name":"Gene Autry"},"song":{"id":"SOLIGLL12AB018C551","title":"Blueberry Hill"}},{"artist":{"name":"Mr. De\u0027"},"song":{"id":"SOCJCPS12AB017D8AE","title":"Please Belive It"}},{"artist":{"name":"Patrizia Pace/Waltraud Meier/Frank Lopardo/James Morris/Swedish Radio Choir/Stockholm Chamber Choir/Berliner Philharmoniker/Riccardo Muti"},"song":{"id":"SOPBKDI12A8C137D8F","title":"Mass No. 19 in D minor_ \u0027Requiem\u0027 K626: Lacrimosa"}},{"artist":{"name":"Robert Palmer"},"song":{"id":"SOJVAKH12AB0184F65","title":"Some Guys Have All The Luck"}},{"artist":{"name":"Christina Aguilera"},"song":{"id":"SOSXJSF12A8C13DD2D","title":"Beautiful"}},{"artist":{"name":"Steve Harvey"},"song":{"id":"SONBZRB12A6D4FA945","title":"What Woman Really Wear To Bed"}},{"artist":{"name":"Cindy Morgan"},"song":{"id":"SOJWWTP12A6D4F8952","title":"I Will Be Free (LP Version)"}},{"artist":{"name":"Gal Costa"},"song":{"id":"SOAVRJE12A58A798CE","title":"Meu Bem Meu Mal (Mi Bien Mi Mal)"}},{"artist":{"name":"David Benoit"},"song":{"id":"SOJKYRI12A58A7D06C","title":"Frieda"}},{"artist":{"name":"32 Leaves"},"song":{"id":"SOZOEUF12AB017E66A","title":"Way Beyond"}},{"artist":{"name":"Rockabye Baby!"},"song":{"id":"SOCBGSL12A8C13747D","title":"You Still Believe in Me"}},{"artist":{"name":"Keep Of Kalessin"},"song":{"id":"SOSTWHL12A6D4FD2A9","title":"As Mist Lay Silent Beneath"}},{"artist":{"name":"Bruce Rowland"},"song":{"id":"SOICOXW12A8C144D5C","title":"You Should Be Free"}},{"artist":{"name":"Delbert McClinton"},"song":{"id":"SOYBVOI12AB017AD6B","title":"Lover In Demand"}},{"artist":{"name":"Wyclef Jean featuring Prodigy of Mobb Deep"},"song":{"id":"SOOYKEK12A8C13B1DD","title":"Rebel Music"}},{"artist":{"name":"The Impressions"},"song":{"id":"SOQLAUY12A6D4F900A","title":"Need To Belong To Someone"}},{"artist":{"name":"Robin Beanland/Dweezil Zappa/Nile Rodgers/Rabbit In The Moon"},"song":{"id":"SOVRIPF12A8C142FD3","title":"Conker The King"}},{"artist":{"name":"Jackie Wilson"},"song":{"id":"SOLZYAI12AC46893E4","title":"Why Can\u0027t You Be Mine"}},{"artist":{"name":"Jason Miles"},"song":{"id":"SOAMLPM12A8C13501C","title":"Street Vibe"}},{"artist":{"name":"Danny Wright"},"song":{"id":"SOOTWRY12AB018277E","title":"Believe"}},{"artist":{"name":"Long Beach Dub Allstars"},"song":{"id":"SOBPHQK12AF72A6AFF","title":"Like A Dog"}},{"artist":{"name":"Cyndi Wang"},"song":{"id":"SOICDVR12AC3DFB6F6","title":"I\u0027ll Be Better"}},{"artist":{"name":"Pablo Montero"},"song":{"id":"SOLRMRV12AB017B887","title":"Jarabe De Pico"}},{"artist":{"name":"Aeoliah"},"song":{"id":"SOEDZFJ12A8C1370AE","title":"Inner Chamber"}},{"artist":{"name":"Beastie Boys"},"song":{"id":"SOHDZDZ12A6D4F7238","title":"Crawlspace"}},{"artist":{"name":"CafA(c) Quijano"},"song":{"id":"SOZSPRJ12A8C13EC7C","title":"En mis besos"}},{"artist":{"name":"The Allies"},"song":{"id":"SOFCVXH12AB0184394","title":"Bewitched_ Bothered \u0026 Bewildered"}},{"artist":{"name":"The Chico Hamilton Quintet"},"song":{"id":"SOGMRON12A8C136042","title":"Night Beat"}},{"artist":{"name":"AndraA(c) Crouch \u0026 Solid Gospel"},"song":{"id":"SOPOCMA12AB018B3A1","title":"My Tribute (to God Be The Glory)"}},{"artist":{"name":"Daddy Yankee / May-Be"},"song":{"id":"SOXWGYN12A6702067A","title":"Que Vas A Hacer?"}},{"artist":{"name":"Robert Lockwood_ Jr."},"song":{"id":"SOYWVRO12AB018353B","title":"Kindhearted Woman Blues"}},{"artist":{"name":"Mudhoney"},"song":{"id":"SOFMBEN12AB0180769","title":"Beneath The Valley Of The Underdog (Album Version + Hidden Track \"Talkin\u0027 Randy Tate\u0027s...\")"}},{"artist":{"name":"Handsome Boy Modeling School"},"song":{"id":"SOOJUIE12A81C212C2","title":"Rock And Roll (Could Never Hip Hop Like This) Part 2 featuring Lord Finesse_ Mike Shonoda_ Chester Bennington_ Rahzel_ Qbert_ Grand Wizard Theodore \u0026 Jazzy Jay (Instrumental)"}},{"artist":{"name":"Jeanne Robertson"},"song":{"id":"SODFJJC12AC468C3F3","title":"Perk trip - sleeping in \"tubes"}},{"artist":{"name":"Sean Paul"},"song":{"id":"SOBEVGM12A67ADBCA7","title":"Baby Boy [feat. Beyonce]"}},{"artist":{"name":"Charlie Byrd / Carlos Barbosa-Lima / Carlos Barbosa-Lima"},"song":{"id":"SOQBRHU12A8C13BCA0","title":"Sarambeque"}},{"artist":{"name":"Otis Spann"},"song":{"id":"SODOBSS12AC9072A5E","title":"Half Ain\u0027t Been Told"}},{"artist":{"name":"A Tribe Called Quest"},"song":{"id":"SOAMYXR12A8C13A8AF","title":"Get A Hold"}},{"artist":{"name":"Toni Braxton"},"song":{"id":"SOZGBWV12A8C137BE5","title":"Best Friend"}},{"artist":{"name":"Nick Ingman;Gavyn Wright"},"song":{"id":"SOJTILF12A8C134ED7","title":"The Beginning of the Partnership"}},{"artist":{"name":"Egberto Gismonti"},"song":{"id":"SOMUFQB12A81C22FA9","title":"Carta De Amor"}},{"artist":{"name":"Margaret Becker"},"song":{"id":"SOHGGKC12A8C130BE4","title":"Sweet Suffering Christ"}},{"artist":{"name":"True Believers"},"song":{"id":"SOTEGPD12A8C135FB7","title":"Just Look At the Blessing"}},{"artist":{"name":"Click / Click_ M_Ferri"},"song":{"id":"SOXHQKT12AB01847E8","title":"Beachport"}},{"artist":{"name":"Rakim feat. Tracey Horton"},"song":{"id":"SOXPCET12AB018D580","title":"Won\u0027t Be Long"}},{"artist":{"name":"Maria \u0026 Margot Hellwig/Die Garmischer AlpenjA$?ger"},"song":{"id":"SOLHGND12AB0189E22","title":"Lieder_ Die Uns Ein Leben Lang Begleiten"}},{"artist":{"name":"Laurie Berkner"},"song":{"id":"SOKPBHZ12AB0181931","title":"The Cat Came Back"}},{"artist":{"name":"A Day To Remember"},"song":{"id":"SOMDCSV12A6D4FCC4E","title":"The Plot To Bomb The Panhandle (Album Version)"}},{"artist":{"name":"The Plasmatics"},"song":{"id":"SOKPHRH12A8C13C0FC","title":"The White\u0027s Bedroom - Fire Escape"}},{"artist":{"name":"Be Bop Deluxe"},"song":{"id":"SOGFWQD12A6D4F6811","title":"Sister Seagull (Live)"}},{"artist":{"name":"Devo"},"song":{"id":"SOBVTQI12A6D4F80ED","title":"Be Stiff (Live)"}},{"artist":{"name":"Abbott \u0026 Chambers"},"song":{"id":"SOTMCYN12AB0183054","title":"Where Are You"}},{"artist":{"name":"Quinteto Violado"},"song":{"id":"SOQINBV12A8C136A80","title":"Maria Betania"}},{"artist":{"name":"Bela Fleck And The Flecktones"},"song":{"id":"SOHRWWQ12AC90727FD","title":"Throwdown At The Hoedown (LP Version)"}},{"artist":{"name":"Egberto Gismonti"},"song":{"id":"SOFCEWK12A6D4F9A19","title":"Baiao Malandro"}},{"artist":{"name":"Danny Barnes"},"song":{"id":"SOOVPDF12AB0182A9A","title":"Cumberland Gap"}},{"artist":{"name":"Usher Featuring The Nu Beginning"},"song":{"id":"SOPJMCP12AB018CCA2","title":"Mother\u0027s Luv"}},{"artist":{"name":"Karen Peck And New River"},"song":{"id":"SOWBRNM12AB018AD0E","title":"I\u0027ll Never Be Able (To Tell It All) (High Key-Studio Track w/o Background Vocals)"}},{"artist":{"name":"David Jalbert"},"song":{"id":"SOYXIYK12A8C138524","title":"Nocturne For Piano No. 8 In D Flat Major_ Op. 84 No. 8 (also in Huit piA\"ces brA\"ves_ Op. 84/8)"}},{"artist":{"name":"Natasha Bedingfield"},"song":{"id":"SOWZGGJ12AAF3B583F","title":"Love Like This"}},{"artist":{"name":"Josh Groban"},"song":{"id":"SOKMZQL12A58A76B19","title":"Believe (Album Version)"}},{"artist":{"name":"Margaret Becker"},"song":{"id":"SOWIGXC12AF729AEC2","title":"O Come_ O Come Emmanuel"}},{"artist":{"name":"Penguin CafA(c) Orchestra"},"song":{"id":"SOYUEBW12A6D4FB3AC","title":"Music By Numbers (2001 Digital Remaster)"}},{"artist":{"name":"Busdriver"},"song":{"id":"SOGAMCD12AB01803F7","title":"Beauty Supply And Demand"}},{"artist":{"name":"Portobello"},"song":{"id":"SOTZEAA12AC468E553","title":"COLD MORNING"}},{"artist":{"name":"David Banner"},"song":{"id":"SOCWCQL12AF72A3A5A","title":"Syrup Sipping (Banner Beat Break)"}},{"artist":{"name":"One Be Lo"},"song":{"id":"SOUTKII12AAF3B1D4F","title":"learn (Album Version)"}},{"artist":{"name":"Ice \u0026 Breeze"},"song":{"id":"SOYEMEE12A8C144815","title":"How It Begins"}},{"artist":{"name":"Bessie Smith"},"song":{"id":"SOCLRHR12A8C134808","title":"Chicago Bound Blues"}},{"artist":{"name":"Ten Years After"},"song":{"id":"SODKENB12A6D4F46AF","title":"50_000 Miles Beneath My Brain (Live)"}},{"artist":{"name":"Behemoth"},"song":{"id":"SOWMVSQ12A8C13E1DC","title":"Malice"}},{"artist":{"name":"Regina Belle"},"song":{"id":"SOMGNHX12A8C131BB0","title":"You Are Everything"}},{"artist":{"name":"The New York Dolls"},"song":{"id":"SOVOEOG12AF729F7DF","title":"Human Being"}},{"artist":{"name":"The Beatles / Tony Sheridan"},"song":{"id":"SOHLPTB12AF72A6B20","title":"Ain\u0027t She Sweet"}},{"artist":{"name":"Pee Wee King"},"song":{"id":"SOVZUYU12AB0183FF1","title":"Tennessee Central Number Nine"}},{"artist":{"name":"Nazz"},"song":{"id":"SOJHDDU12A8C143F70","title":"It Must Be Everywhere (Complete Version)"}},{"artist":{"name":"FlA$?skkvartetten / Daniel Bellqvist"},"song":{"id":"SOIIAIE12A8C13C5FC","title":"You Were There"}},{"artist":{"name":"Robert Palmer"},"song":{"id":"SOCMLII12A6D4FAB7F","title":"Man Smart Woman Smarter"}},{"artist":{"name":"Precious Bryant"},"song":{"id":"SOAHARW12AB017BAE8","title":"Blues All Around My Bed"}},{"artist":{"name":"Klubbingman feat. Beatrix Delgado"},"song":{"id":"SOUZLSE12AB0184B1D","title":"Another Day Another Night"}},{"artist":{"name":"David Guetta - Joachim Garraud - Chris Willis"},"song":{"id":"SONXJXB12A8C138151","title":"Love Is Gone (Eddie Thoneick\u0027s Liberte Mix)"}},{"artist":{"name":"Anti-Flag"},"song":{"id":"SOTRPCV12A6D4FAB31","title":"I Don\u0027t Wanna be a War Hero"}},{"artist":{"name":"Pelt"},"song":{"id":"SOLXFEV12A58A7AE81","title":"Bestio Tergum Degero Pt. 3"}},{"artist":{"name":"Dr. Elmo"},"song":{"id":"SOGHVNS12A8C139B59","title":"Christmas Won\u0027t be the Same Without Johnny"}},{"artist":{"name":"David Jalbert"},"song":{"id":"SODXQQY12A8C13850E","title":"Nocturne For Piano No. 5 In B Flat Major_ Op. 37"}},{"artist":{"name":"VHS Or Beta"},"song":{"id":"SOJLTFB12A6D4F91FC","title":"Forever"}},{"artist":{"name":"Be Bop Deluxe"},"song":{"id":"SOJCSXO12A8C13A80B","title":"Music In Dreamland"}},{"artist":{"name":"Clara Nunes"},"song":{"id":"SOHLLRA12A6D4F7DBA","title":"Zambele (1997 Digital Remaster)"}},{"artist":{"name":"Warrant"},"song":{"id":"SOTOSFD12AB017A7E1","title":"Bed Of Roses"}},{"artist":{"name":"Steel Pulse"},"song":{"id":"SOBFZKC12A6D4FC1F7","title":"Man No Sober (LP Version)"}},{"artist":{"name":"Phil Vassar"},"song":{"id":"SOGAIRT12A58291E2D","title":"Like I Never Loved Before"}},{"artist":{"name":"Najoua Belyzel"},"song":{"id":"SOHABTD12AB0186D83","title":"Ma vie n\u0027est pas la tienne (album)"}},{"artist":{"name":"Bobby Darin"},"song":{"id":"SOGOLHP12A8AE47A0D","title":"Theme From \"Come September\" (LP Version)"}},{"artist":{"name":"Seventh Day Slumber"},"song":{"id":"SOPBEBP12AB0181527","title":"Famous One"}},{"artist":{"name":"Will Ackerman"},"song":{"id":"SOYLDNP12A8C13C135","title":"A Movie Of A Placid Lake On A Moonless Night in September"}},{"artist":{"name":"Virtuoso"},"song":{"id":"SOQLQUB12A58A7E448","title":"Rakkahin -Be My Love-"}},{"artist":{"name":"New York Dolls"},"song":{"id":"SOKRZJY12AB0187E80","title":"Human Being (1972 demo)"}},{"artist":{"name":"Behemoth"},"song":{"id":"SOPVZSM12A8C13E1F1","title":"Hello Space Boy"}},{"artist":{"name":"Marc Shaiman"},"song":{"id":"SODRGUS12A8C13312C","title":"Best In LA"}},{"artist":{"name":"bel canto"},"song":{"id":"SOBEHXG12A8C138D22","title":"Rumour (Abstract Hip Hop Mix)"}},{"artist":{"name":"Cachao"},"song":{"id":"SOMYXTW12A8C130319","title":"Los Tres Glopes / The Three Beats (danza)"}},{"artist":{"name":"Mustafa Sandal"},"song":{"id":"SOWESXJ12A8C136BEC","title":"Beni Aglatma"}},{"artist":{"name":"Beneath The Sky"},"song":{"id":"SOJBELS12A6D4FCE9A","title":"No Such Thing As Control (Album Version)"}},{"artist":{"name":"Sex Pistols"},"song":{"id":"SOBBQDL12A58A7A988","title":"100 Club 1996 \u0027\u0027We Love You Beatles\u0027\u0027 - Live"}},{"artist":{"name":"[kaleidoskop]"},"song":{"id":"SOSTZFN12AC468E3F1","title":"deine liebe"}},{"artist":{"name":"Bedrock"},"song":{"id":"SOKMTOP12AC468980A","title":"Emerald"}},{"artist":{"name":"Radio Birdman"},"song":{"id":"SOGAWLI12AB017E8AB","title":"Zeno Beach"}},{"artist":{"name":"30 Seconds To Mars"},"song":{"id":"SOCHUHK12A6D4F7883","title":"End Of The Beginning"}},{"artist":{"name":"Marco Beltrami"},"song":{"id":"SOOOBPU12A6D4FC54A","title":"1001 Robots"}},{"artist":{"name":"Bad Religion"},"song":{"id":"SOWYQOV12AF729E1A1","title":"You Don\u0027t Belong"}},{"artist":{"name":"Ben Jelen"},"song":{"id":"SOGIUWE12A670215DC","title":"Come On (Sessions@AOL Version)"}},{"artist":{"name":"Vulture Industries"},"song":{"id":"SOAHRTY12AC468AF45","title":"The Benevolent Path"}},{"artist":{"name":"BeyoncA(c)"},"song":{"id":"SOBCMRK12A8AE488DF","title":"Dangerously In Love Medley"}},{"artist":{"name":"MichA\"le Bernard"},"song":{"id":"SOBIQZV12A8C14345A","title":"Amour noir N 7"}},{"artist":{"name":"Frank Ifield"},"song":{"id":"SODGOBW12AB01803D3","title":"I\u0027ll Be Around"}},{"artist":{"name":"The Jackson Southernaires"},"song":{"id":"SODDJEB12A8AE479D8","title":"Somewhere In Between"}},{"artist":{"name":"K\u0027s Choice"},"song":{"id":"SOONMNI12A8C134D2D","title":"God In My Bed"}},{"artist":{"name":"Bonita"},"song":{"id":"SOPLSRU12AB018860D","title":"It Could Never Be You"}},{"artist":{"name":"Ann Nesby / Jamecia Bennett"},"song":{"id":"SOTHXZR12A6D4FAA86","title":"Advice"}},{"artist":{"name":"Twenty 4 Seven"},"song":{"id":"SOGCGLF12AC907171E","title":"You Gotta Be Safe"}},{"artist":{"name":"Atienne Daho"},"song":{"id":"SOLPOGC12AB017D41F","title":"Cet Air Atrange (Take 1 - Abbey Road Rough Mix)"}},{"artist":{"name":"Cookies"},"song":{"id":"SOMKHUF12AB0180C5E","title":"Believe In What I Say"}},{"artist":{"name":"Erik Berglund"},"song":{"id":"SODWYEY12AC468C30F","title":"Endless Light"}},{"artist":{"name":"Hank Locklin"},"song":{"id":"SOVIMXL12AB01860DE","title":"Let Me Be the One"}},{"artist":{"name":"Cockney Rejects"},"song":{"id":"SOKCJMY12A8C1449C1","title":"Beginning Of The End"}},{"artist":{"name":"Archie Bell and The Drells"},"song":{"id":"SOXBVUJ12A8C13CB38","title":"I\u0027ve Been Trying"}},{"artist":{"name":"Benabar"},"song":{"id":"SOUYOSU12A8C139214","title":"Porcelaine"}},{"artist":{"name":"Montserrat CaballA(c)/Orchestra of the Royal Opera House_ Covent Garden/Carlo Maria Giulini"},"song":{"id":"SOFYJJG12A8BEE9583","title":"Don Carlo (2000 Digital Remaster): Tu che le vanitA  (Elisabetta)"}},{"artist":{"name":"Beogradski Sindikat"},"song":{"id":"SOGAGGI12AB0183FC6","title":"Slatke male maloletnice"}},{"artist":{"name":"Laurie Berkner"},"song":{"id":"SOHCSSG12A58A7CF2D","title":"I\u0027ve Been Working on the Railroad"}},{"artist":{"name":"Glen Washington"},"song":{"id":"SOTLPCJ12AB0189D0C","title":"Number One Girl"}},{"artist":{"name":"Luis Alberto Spinetta"},"song":{"id":"SOXYIJD12A8C13DB7C","title":"Lo Siento En Mi CorazA3n"}},{"artist":{"name":"Gal Costa / Maria BethAC/nia"},"song":{"id":"SOBTSWX12AC46891BB","title":"Filosofia Pura"}},{"artist":{"name":"Long Beach Dub Allstars"},"song":{"id":"SOSCQEX12A6D4F965A","title":"Free Love"}},{"artist":{"name":"X (Australia)"},"song":{"id":"SOJKIPU12A8C137B47","title":"It Must Be Me"}},{"artist":{"name":"Queens Of The Stone Age"},"song":{"id":"SOKESRD12A6701E91C","title":"Everybody\u0027s Gonna Be Happy"}},{"artist":{"name":"JoAPSo Gilberto"},"song":{"id":"SOKGCRN12AC468D603","title":"ManhAPS de Carnaval (Morning of the Carnaval) (Cantando As MAosicas do Film Orfeo do Carnaval)"}},{"artist":{"name":"Charlie Louvin"},"song":{"id":"SORLGJC12A8C13FADC","title":"I\u0027ll Be Home When I Can"}},{"artist":{"name":"3 Doors Down"},"song":{"id":"SOHGPEC12A8C13BBE8","title":"Better Life"}},{"artist":{"name":"Vienna Concert House Orchestra_ Wiener SA$?ngerknaben_ Ferdinand Grossmann"},"song":{"id":"SOJZHQO12AB0184E36","title":"Requiem Mass in D Minor_ K. 626: VIII. Lacrimosa dies illae"}},{"artist":{"name":"Leroy Hutson"},"song":{"id":"SOBRAEX12A6D4F8F86","title":"Could This Be Love"}},{"artist":{"name":"Elizabeth Cotten"},"song":{"id":"SOPKFPV12A8C141BA2","title":"Elizabeth Story_ et al._ Honeybabe_ Your Papa Cares For You"}},{"artist":{"name":"Van Halen"},"song":{"id":"SOPDFZN12A670215C4","title":"Why Can\u0027t This Be Love (Remastered Version)"}},{"artist":{"name":"Porter Wagoner"},"song":{"id":"SOGQEED12A8C13FCDB","title":"I Can\u0027t Be Your Man"}},{"artist":{"name":"Bert Kaempfert"},"song":{"id":"SOBVTWE12AB01872C8","title":"Happy Safari"}},{"artist":{"name":"Dobet GnahorA(c)"},"song":{"id":"SOXNYWA12AB01877E8","title":"Evigne"}},{"artist":{"name":"Kathy Troccoli with Aaron Jeoffrey"},"song":{"id":"SOLAARS12A58A7786C","title":"I Remember/Great Is Thy Faithfulness"}},{"artist":{"name":"ThA(c)ophil"},"song":{"id":"SOPEPYA12AC90758FA","title":"De belles"}},{"artist":{"name":"Madonna"},"song":{"id":"SOPOCDY12A8C13F75A","title":"4 Minutes [Featuring Justin Timberlake 